Workbook

Sheet Start Here
A1: Inventory Tracker Studio
A2: Start with Setup, then use Inventory to decide what to reorder, when, and how much.
A4: What to do first | D4: Editable areas
A5: 1. Set your review date, lead time, safety stock days, pack size, fees, and target margin in Setup. | D5: Setup input cells
A6: 2. Edit the yellow cells on Inventory for your stock, suppliers, and reorder points. | D6: Inventory opening stock, reorder point, and unit cost
A7: 3. Enter purchases and sales in the log tabs; stock and profit will update automatically. | D7: Purchase log rows
A8: 4. Use Inventory to see reorder action, reorder-by date, projected stockout, days of cover, and suggested order quantity. | D8: Sales log rows
A9: 5. Use Price Calculator to test sale prices before you list items. | D9: Price Calculator inputs
D11: Leave alone
D12: Dashboard formulas and charts
A13: Recovery | D13: Inventory status formulas
A14: Keep a clean copy before heavy edits. If you damage formulas, start again from a fresh duplicate. | D14: Sales profit formulas
D15: Price List snapshot formulas
A16: What this is not
A17: • Not a subscription app | D17: Seeded capacity
A18: • Not bank-connected | D18: 100 inventory rows, 300 purchase rows, 500 sales rows, 100 price calculator rows, and 100 price list rows.
A19: • Not tax or accounting advice
A20: • Not a live inventory service

Sheet Dashboard
A1: Dashboard
A2: The replenishment decision surface: what to reorder, when, and how much.
B4: Inventory rows | D4: Order now | F4: Order qty | H4: Inventory value | J4: Purchase spend | L4: Sales revenue | N4: Gross profit
B5: =COUNTA(Inventory!A5:A104) | D5: =COUNTIF(Inventory!S5:S104,"Order now") | F5: =SUM(Inventory!Q5:Q104) | H5: =SUM(Inventory!K5:K104) | J5: =SUM(Purchases!G5:G304) | L5: =SUM(Sales!G5:G504) | N5: =SUM(Sales!I5:I504)
A8: Reorder action mix
A9: Status | B9: Count
A10: Order now | B10: =COUNTIF(Inventory!S5:S104,"Order now")
A11: Order this week | B11: =COUNTIF(Inventory!S5:S104,"Order this week")
A12: Plan reorder | B12: =COUNTIF(Inventory!S5:S104,"Plan reorder")
A13: No action | B13: =COUNTIF(Inventory!S5:S104,"No action")
A16: Top notes
A17: • Use Setup first, then Inventory.
A18: • Inventory outputs reorder action, reorder-by date, projected stockout date, days cover, suggested order qty, velocity, lead time, and safety stock.
A19: • Seeded capacity: 100 inventory rows, 300 purchase rows, 500 sales rows, 100 calculator rows, 100 price-list rows.
A20: • Purchases raise stock; Sales lower stock.
A21: • Price Calculator helps you test margins before listing.
A22: • Price List stores the approved price snapshot.

Sheet Setup
A1: Setup
A2: Choose the defaults that drive replenishment, stock, and pricing formulas.
A4: Currency symbol | B4: $ | D4: Categories
A5: Review date | B5: 46096 | D5: Accessories, Drinkware, Stationery, Home, Wall Art, Apparel
A6: Sales lookback days | B6: 30
A7: Sales tax | B7: 0.1 | D7: Editable cells
A8: Marketplace fee | B8: 0.13 | D8: Yellow input cells in Setup, Inventory, Purchases, Sales, and Price Calculator.
A9: Target margin | B9: 0.45
A10: Default reorder point | B10: 10
A11: Lead time days | B11: 14
A12: Safety stock days | B12: 7
A13: Default pack size | B13: 6 | D13: Workbook capacity
A14: Support note | B14: Use the workbook for stock, purchases, sales, and pricing. | D14: The delivered workbook ships with 100 inventory rows, 300 purchase rows, 500 sales rows, 100 calculator rows, and 100 price-list rows.
D16: Unsupported
D17: Live bank sync, tax filing, and custom bookkeeping.

Sheet Inventory
A1: Inventory
A2: Decide what to reorder, when to reorder it, and how much to buy.
A4: SKU | B4: Item | C4: Category | D4: Supplier | E4: Opening Stock | F4: Purchases | G4: Sales | H4: On Hand | I4: Reorder Point | J4: Unit Cost | K4: Inventory Value | L4: Sales Velocity/Day | M4: Days Cover | N4: Projected Stockout | O4: Lead Time Used | P4: Safety Stock | Q4: Suggested Order Qty | R4: Reorder By | S4: Reorder Action | T4: Status | U4: Notes
A5: SKU-001 | B5: Canvas Tote - Sand | C5: Accessories | D5: Northstar Wholesale | E5: 2 | F5: =SUMIFS(Purchases!$D$5:$D$304,Purchases!$B$5:$B$304,$A5) | G5: =SUMIFS(Sales!$D$5:$D$504,Sales!$B$5:$B$504,$A5) | H5: =E5+F5-G5 | I5: 12 | J5: 0.95 | K5: =H5*J5 | L5: =IFERROR(SUMIFS(Sales!$D$5:$D$504,Sales!$B$5:$B$504,$A5,Sales!$A$5:$A$504,">="&Setup!$B$5-Setup!$B$6,Sales!$A$5:$A$504,"<="&Setup!$B$5)/Setup!$B$6,0) | M5: =IF(L5<=0,999,H5/L5) | N5: =IF(L5<=0,"No recent sales",Setup!$B$5+M5) | O5: =Setup!$B$11 | P5: =ROUNDUP(L5*Setup!$B$12,0) | Q5: =IF(MAX(0,ROUNDUP((L5*(O5+Setup!$B$12))-H5,0))=0,0,CEILING(MAX(0,ROUNDUP((L5*(O5+Setup!$B$12))-H5,0)),Setup!$B$13)) | R5: =IF(L5<=0,"No sales signal",N5-O5) | S5: =IF(H5<=0,"Order now",IF(R5="No sales signal","No action",IF(R5<=Setup!$B$5,"Order now",IF(R5<=Setup!$B$5+7,"Order this week",IF(H5<=I5,"Plan reorder","No action"))))) | T5: =IF(H5<=0,"Out of stock",IF(H5<=I5,"Reorder soon","Healthy")) | U5: Reusable carry tote / batch 1
A6: SKU-002 | B6: Canvas Tote - Olive | C6: Accessories | D6: Northstar Wholesale | E6: 3 | F6: =SUMIFS(Purchases!$D$5:$D$304,Purchases!$B$5:$B$304,$A6) | G6: =SUMIFS(Sales!$D$5:$D$504,Sales!$B$5:$B$504,$A6) | H6: =E6+F6-G6 | I6: 13 | J6: 1.12 | K6: =H6*J6 | L6: =IFERROR(SUMIFS(Sales!$D$5:$D$504,Sales!$B$5:$B$504,$A6,Sales!$A$5:$A$504,">="&Setup!$B$5-Setup!$B$6,Sales!$A$5:$A$504,"<="&Setup!$B$5)/Setup!$B$6,0) | M6: =IF(L6<=0,999,H6/L6) | N6: =IF(L6<=0,"No recent sales",Setup!$B$5+M6) | O6: =Setup!$B$11 | P6: =ROUNDUP(L6*Setup!$B$12,0) | Q6: =IF(MAX(0,ROUNDUP((L6*(O6+Setup!$B$12))-H6,0))=0,0,CEILING(MAX(0,ROUNDUP((L6*(O6+Setup!$B$12))-H6,0)),Setup!$B$13)) | R6: =IF(L6<=0,"No sales signal",N6-O6) | S6: =IF(H6<=0,"Order now",IF(R6="No sales signal","No action",IF(R6<=Setup!$B$5,"Order now",IF(R6<=Setup!$B$5+7,"Order this week",IF(H6<=I6,"Plan reorder","No action"))))) | T6: =IF(H6<=0,"Out of stock",IF(H6<=I6,"Reorder soon","Healthy")) | U6: Reusable carry tote / batch 1
A7: SKU-003 | B7: Canvas Tote - Slate | C7: Accessories | D7: Northstar Wholesale | E7: 2 | F7: =SUMIFS(Purchases!$D$5:$D$304,Purchases!$B$5:$B$304,$A7) | G7: =SUMIFS(Sales!$D$5:$D$504,Sales!$B$5:$B$504,$A7) | H7: =E7+F7-G7 | I7: 14 | J7: 1.29 | K7: =H7*J7 | L7: =IFERROR(SUMIFS(Sales!$D$5:$D$504,Sales!$B$5:$B$504,$A7,Sales!$A$5:$A$504,">="&Setup!$B$5-Setup!$B$6,Sales!$A$5:$A$504,"<="&Setup!$B$5)/Setup!$B$6,0) | M7: =IF(L7<=0,999,H7/L7) | N7: =IF(L7<=0,"No recent sales",Setup!$B$5+M7) | O7: =Setup!$B$11 | P7: =ROUNDUP(L7*Setup!$B$12,0) | Q7: =IF(MAX(0,ROUNDUP((L7*(O7+Setup!$B$12))-H7,0))=0,0,CEILING(MAX(0,ROUNDUP((L7*(O7+Setup!$B$12))-H7,0)),Setup!$B$13)) | R7: =IF(L7<=0,"No sales signal",N7-O7) | S7: =IF(H7<=0,"Order now",IF(R7="No sales signal","No action",IF(R7<=Setup!$B$5,"Order now",IF(R7<=Setup!$B$5+7,"Order this week",IF(H7<=I7,"Plan reorder","No action"))))) | T7: =IF(H7<=0,"Out of stock",IF(H7<=I7,"Reorder soon","Healthy")) | U7: Reusable carry tote / batch 1
A8: SKU-004 | B8: Canvas Tote - Coral | C8: Accessories | D8: Northstar Wholesale | E8: 3 | F8: =SUMIFS(Purchases!$D$5:$D$304,Purchases!$B$5:$B$304,$A8) | G8: =SUMIFS(Sales!$D$5:$D$504,Sales!$B$5:$B$504,$A8) | H8: =E8+F8-G8 | I8: 15 | J8: 1.46 | K8: =H8*J8 | L8: =IFERROR(SUMIFS(Sales!$D$5:$D$504,Sales!$B$5:$B$504,$A8,Sales!$A$5:$A$504,">="&Setup!$B$5-Setup!$B$6,Sales!$A$5:$A$504,"<="&Setup!$B$5)/Setup!$B$6,0) | M8: =IF(L8<=0,999,H8/L8) | N8: =IF(L8<=0,"No recent sales",Setup!$B$5+M8) | O8: =Setup!$B$11 | P8: =ROUNDUP(L8*Setup!$B$12,0) | Q8: =IF(MAX(0,ROUNDUP((L8*(O8+Setup!$B$12))-H8,0))=0,0,CEILING(MAX(0,ROUNDUP((L8*(O8+Setup!$B$12))-H8,0)),Setup!$B$13)) | R8: =IF(L8<=0,"No sales signal",N8-O8) | S8: =IF(H8<=0,"Order now",IF(R8="No sales signal","No action",IF(R8<=Setup!$B$5,"Order now",IF(R8<=Setup!$B$5+7,"Order this week",IF(H8<=I8,"Plan reorder","No action"))))) | T8: =IF(H8<=0,"Out of stock",IF(H8<=I8,"Reorder soon","Healthy")) | U8: Reusable carry tote / batch 1
A9: SKU-005 | B9: Canvas Tote - Natural | C9: Accessories | D9: Northstar Wholesale | E9: 11 | F9: =SUMIFS(Purchases!$D$5:$D$304,Purchases!$B$5:$B$304,$A9) | G9: =SUMIFS(Sales!$D$5:$D$504,Sales!$B$5:$B$504,$A9) | H9: =E9+F9-G9 | I9: 12 | J9: 1.63 | K9: =H9*J9 | L9: =IFERROR(SUMIFS(Sales!$D$5:$D$504,Sales!$B$5:$B$504,$A9,Sales!$A$5:$A$504,">="&Setup!$B$5-Setup!$B$6,Sales!$A$5:$A$504,"<="&Setup!$B$5)/Setup!$B$6,0) | M9: =IF(L9<=0,999,H9/L9) | N9: =IF(L9<=0,"No recent sales",Setup!$B$5+M9) | O9: =Setup!$B$11 | P9: =ROUNDUP(L9*Setup!$B$12,0) | Q9: =IF(MAX(0,ROUNDUP((L9*(O9+Setup!$B$12))-H9,0))=0,0,CEILING(MAX(0,ROUNDUP((L9*(O9+Setup!$B$12))-H9,0)),Setup!$B$13)) | R9: =IF(L9<=0,"No sales signal",N9-O9) | S9: =IF(H9<=0,"Order now",IF(R9="No sales signal","No action",IF(R9<=Setup!$B$5,"Order now",IF(R9<=Setup!$B$5+7,"Order this week",IF(H9<=I9,"Plan reorder","No action"))))) | T9: =IF(H9<=0,"Out of stock",IF(H9<=I9,"Reorder soon","Healthy")) | U9: Reusable carry tote / batch 1
A10: SKU-006 | B10: Ceramic Mug - Sand | C10: Drinkware | D10: Harbor Supply | E10: 12 | F10: =SUMIFS(Purchases!$D$5:$D$304,Purchases!$B$5:$B$304,$A10) | G10: =SUMIFS(Sales!$D$5:$D$504,Sales!$B$5:$B$504,$A10) | H10: =E10+F10-G10 | I10: 11 | J10: 2.1 | K10: =H10*J10 | L10: =IFERROR(SUMIFS(Sales!$D$5:$D$504,Sales!$B$5:$B$504,$A10,Sales!$A$5:$A$504,">="&Setup!$B$5-Setup!$B$6,Sales!$A$5:$A$504,"<="&Setup!$B$5)/Setup!$B$6,0) | M10: =IF(L10<=0,999,H10/L10) | N10: =IF(L10<=0,"No recent sales",Setup!$B$5+M10) | O10: =Setup!$B$11 | P10: =ROUNDUP(L10*Setup!$B$12,0) | Q10: =IF(MAX(0,ROUNDUP((L10*(O10+Setup!$B$12))-H10,0))=0,0,CEILING(MAX(0,ROUNDUP((L10*(O10+Setup!$B$12))-H10,0)),Setup!$B$13)) | R10: =IF(L10<=0,"No sales signal",N10-O10) | S10: =IF(H10<=0,"Order now",IF(R10="No sales signal","No action",IF(R10<=Setup!$B$5,"Order now",IF(R10<=Setup!$B$5+7,"Order this week",IF(H10<=I10,"Plan reorder","No action"))))) | T10: =IF(H10<=0,"Out of stock",IF(H10<=I10,"Reorder soon","Healthy")) | U10: Gloss finish mug / batch 1
A11: SKU-007 | B11: Ceramic Mug - Olive | C11: Drinkware | D11: Harbor Supply | E11: 10 | F11: =SUMIFS(Purchases!$D$5:$D$304,Purchases!$B$5:$B$304,$A11) | G11: =SUMIFS(Sales!$D$5:$D$504,Sales!$B$5:$B$504,$A11) | H11: =E11+F11-G11 | I11: 12 | J11: 2.27 | K11: =H11*J11 | L11: =IFERROR(SUMIFS(Sales!$D$5:$D$504,Sales!$B$5:$B$504,$A11,Sales!$A$5:$A$504,">="&Setup!$B$5-Setup!$B$6,Sales!$A$5:$A$504,"<="&Setup!$B$5)/Setup!$B$6,0) | M11: =IF(L11<=0,999,H11/L11) | N11: =IF(L11<=0,"No recent sales",Setup!$B$5+M11) | O11: =Setup!$B$11 | P11: =ROUNDUP(L11*Setup!$B$12,0) | Q11: =IF(MAX(0,ROUNDUP((L11*(O11+Setup!$B$12))-H11,0))=0,0,CEILING(MAX(0,ROUNDUP((L11*(O11+Setup!$B$12))-H11,0)),Setup!$B$13)) | R11: =IF(L11<=0,"No sales signal",N11-O11) | S11: =IF(H11<=0,"Order now",IF(R11="No sales signal","No action",IF(R11<=Setup!$B$5,"Order now",IF(R11<=Setup!$B$5+7,"Order this week",IF(H11<=I11,"Plan reorder","No action"))))) | T11: =IF(H11<=0,"Out of stock",IF(H11<=I11,"Reorder soon","Healthy")) | U11: Gloss finish mug / batch 1
A12: SKU-008 | B12: Ceramic Mug - Slate | C12: Drinkware | D12: Harbor Supply | E12: 11 | F12: =SUMIFS(Purchases!$D$5:$D$304,Purchases!$B$5:$B$304,$A12) | G12: =SUMIFS(Sales!$D$5:$D$504,Sales!$B$5:$B$504,$A12) | H12: =E12+F12-G12 | I12: 13 | J12: 2.44 | K12: =H12*J12 | L12: =IFERROR(SUMIFS(Sales!$D$5:$D$504,Sales!$B$5:$B$504,$A12,Sales!$A$5:$A$504,">="&Setup!$B$5-Setup!$B$6,Sales!$A$5:$A$504,"<="&Setup!$B$5)/Setup!$B$6,0) | M12: =IF(L12<=0,999,H12/L12) | N12: =IF(L12<=0,"No recent sales",Setup!$B$5+M12) | O12: =Setup!$B$11 | P12: =ROUNDUP(L12*Setup!$B$12,0) | Q12: =IF(MAX(0,ROUNDUP((L12*(O12+Setup!$B$12))-H12,0))=0,0,CEILING(MAX(0,ROUNDUP((L12*(O12+Setup!$B$12))-H12,0)),Setup!$B$13)) | R12: =IF(L12<=0,"No sales signal",N12-O12) | S12: =IF(H12<=0,"Order now",IF(R12="No sales signal","No action",IF(R12<=Setup!$B$5,"Order now",IF(R12<=Setup!$B$5+7,"Order this week",IF(H12<=I12,"Plan reorder","No action"))))) | T12: =IF(H12<=0,"Out of stock",IF(H12<=I12,"Reorder soon","Healthy")) | U12: Gloss finish mug / batch 1
A13: SKU-009 | B13: Ceramic Mug - Coral | C13: Drinkware | D13: Harbor Supply | E13: 12 | F13: =SUMIFS(Purchases!$D$5:$D$304,Purchases!$B$5:$B$304,$A13) | G13: =SUMIFS(Sales!$D$5:$D$504,Sales!$B$5:$B$504,$A13) | H13: =E13+F13-G13 | I13: 10 | J13: 2.61 | K13: =H13*J13 | L13: =IFERROR(SUMIFS(Sales!$D$5:$D$504,Sales!$B$5:$B$504,$A13,Sales!$A$5:$A$504,">="&Setup!$B$5-Setup!$B$6,Sales!$A$5:$A$504,"<="&Setup!$B$5)/Setup!$B$6,0) | M13: =IF(L13<=0,999,H13/L13) | N13: =IF(L13<=0,"No recent sales",Setup!$B$5+M13) | O13: =Setup!$B$11 | P13: =ROUNDUP(L13*Setup!$B$12,0) | Q13: =IF(MAX(0,ROUNDUP((L13*(O13+Setup!$B$12))-H13,0))=0,0,CEILING(MAX(0,ROUNDUP((L13*(O13+Setup!$B$12))-H13,0)),Setup!$B$13)) | R13: =IF(L13<=0,"No sales signal",N13-O13) | S13: =IF(H13<=0,"Order now",IF(R13="No sales signal","No action",IF(R13<=Setup!$B$5,"Order now",IF(R13<=Setup!$B$5+7,"Order this week",IF(H13<=I13,"Plan reorder","No action"))))) | T13: =IF(H13<=0,"Out of stock",IF(H13<=I13,"Reorder soon","Healthy")) | U13: Gloss finish mug / batch 1
A14: SKU-010 | B14: Ceramic Mug - Natural | C14: Drinkware | D14: Harbor Supply | E14: 10 | F14: =SUMIFS(Purchases!$D$5:$D$304,Purchases!$B$5:$B$304,$A14) | G14: =SUMIFS(Sales!$D$5:$D$504,Sales!$B$5:$B$504,$A14) | H14: =E14+F14-G14 | I14: 11 | J14: 2.78 | K14: =H14*J14 | L14: =IFERROR(SUMIFS(Sales!$D$5:$D$504,Sales!$B$5:$B$504,$A14,Sales!$A$5:$A$504,">="&Setup!$B$5-Setup!$B$6,Sales!$A$5:$A$504,"<="&Setup!$B$5)/Setup!$B$6,0) | M14: =IF(L14<=0,999,H14/L14) | N14: =IF(L14<=0,"No recent sales",Setup!$B$5+M14) | O14: =Setup!$B$11 | P14: =ROUNDUP(L14*Setup!$B$12,0) | Q14: =IF(MAX(0,ROUNDUP((L14*(O14+Setup!$B$12))-H14,0))=0,0,CEILING(MAX(0,ROUNDUP((L14*(O14+Setup!$B$12))-H14,0)),Setup!$B$13)) | R14: =IF(L14<=0,"No sales signal",N14-O14) | S14: =IF(H14<=0,"Order now",IF(R14="No sales signal","No action",IF(R14<=Setup!$B$5,"Order now",IF(R14<=Setup!$B$5+7,"Order this week",IF(H14<=I14,"Plan reorder","No action"))))) | T14: =IF(H14<=0,"Out of stock",IF(H14<=I14,"Reorder soon","Healthy")) | U14: Gloss finish mug / batch 1
A15: SKU-011 | B15: A5 Notebook - Sand | C15: Stationery | D15: Paper Trail Co. | E15: 43 | F15: =SUMIFS(Purchases!$D$5:$D$304,Purchases!$B$5:$B$304,$A15) | G15: =SUMIFS(Sales!$D$5:$D$504,Sales!$B$5:$B$504,$A15) | H15: =E15+F15-G15 | I15: 20 | J15: 1.25 | K15: =H15*J15 | L15: =IFERROR(SUMIFS(Sales!$D$5:$D$504,Sales!$B$5:$B$504,$A15,Sales!$A$5:$A$504,">="&Setup!$B$5-Setup!$B$6,Sales!$A$5:$A$504,"<="&Setup!$B$5)/Setup!$B$6,0) | M15: =IF(L15<=0,999,H15/L15) | N15: =IF(L15<=0,"No recent sales",Setup!$B$5+M15) | O15: =Setup!$B$11 | P15: =ROUNDUP(L15*Setup!$B$12,0) | Q15: =IF(MAX(0,ROUNDUP((L15*(O15+Setup!$B$12))-H15,0))=0,0,CEILING(MAX(0,ROUNDUP((L15*(O15+Setup!$B$12))-H15,0)),Setup!$B$13)) | R15: =IF(L15<=0,"No sales signal",N15-O15) | S15: =IF(H15<=0,"Order now",IF(R15="No sales signal","No action",IF(R15<=Setup!$B$5,"Order now",IF(R15<=Setup!$B$5+7,"Order this week",IF(H15<=I15,"Plan reorder","No action"))))) | T15: =IF(H15<=0,"Out of stock",IF(H15<=I15,"Reorder soon","Healthy")) | U15: Sewn binding notebook / batch 1
A16: SKU-012 | B16: A5 Notebook - Olive | C16: Stationery | D16: Paper Trail Co. | E16: 45 | F16: =SUMIFS(Purchases!$D$5:$D$304,Purchases!$B$5:$B$304,$A16) | G16: =SUMIFS(Sales!$D$5:$D$504,Sales!$B$5:$B$504,$A16) | H16: =E16+F16-G16 | I16: 21 | J16: 1.42 | K16: =H16*J16 | L16: =IFERROR(SUMIFS(Sales!$D$5:$D$504,Sales!$B$5:$B$504,$A16,Sales!$A$5:$A$504,">="&Setup!$B$5-Setup!$B$6,Sales!$A$5:$A$504,"<="&Setup!$B$5)/Setup!$B$6,0) | M16: =IF(L16<=0,999,H16/L16) | N16: =IF(L16<=0,"No recent sales",Setup!$B$5+M16) | O16: =Setup!$B$11 | P16: =ROUNDUP(L16*Setup!$B$12,0) | Q16: =IF(MAX(0,ROUNDUP((L16*(O16+Setup!$B$12))-H16,0))=0,0,CEILING(MAX(0,ROUNDUP((L16*(O16+Setup!$B$12))-H16,0)),Setup!$B$13)) | R16: =IF(L16<=0,"No sales signal",N16-O16) | S16: =IF(H16<=0,"Order now",IF(R16="No sales signal","No action",IF(R16<=Setup!$B$5,"Order now",IF(R16<=Setup!$B$5+7,"Order this week",IF(H16<=I16,"Plan reorder","No action"))))) | T16: =IF(H16<=0,"Out of stock",IF(H16<=I16,"Reorder soon","Healthy")) | U16: Sewn binding notebook / batch 1
... A104: SKU-100 | B104: Tea Tin - Natural | C104: Home | D104: Harbor Supply | E104: 31 | F104: =SUMIFS(Purchases!$D$5:$D$304,Purchases!$B$5:$B$304,$A104) | G104: =SUMIFS(Sales!$D$5:$D$504,Sales!$B$5:$B$504,$A104) | H104: =E104+F104-G104 | I104: 11 | J104: 2.87 | K104: =H104*J104 | L104: =IFERROR(SUMIFS(Sales!$D$5:$D$504,Sales!$B$5:$B$504,$A104,Sales!$A$5:$A$504,">="&Setup!$B$5-Setup!$B$6,Sales!$A$5:$A$504,"<="&Setup!$B$5)/Setup!$B$6,0) | M104: =IF(L104<=0,999,H104/L104) | N104: =IF(L104<=0,"No recent sales",Setup!$B$5+M104) | O104: =Setup!$B$11 | P104: =ROUNDUP(L104*Setup!$B$12,0) | Q104: =IF(MAX(0,ROUNDUP((L104*(O104+Setup!$B$12))-H104,0))=0,0,CEILING(MAX(0,ROUNDUP((L104*(O104+Setup!$B$12))-H104,0)),Setup!$B$13)) | R104: =IF(L104<=0,"No sales signal",N104-O104) | S104: =IF(H104<=0,"Order now",IF(R104="No sales signal","No action",IF(R104<=Setup!$B$5,"Order now",IF(R104<=Setup!$B$5+7,"Order this week",IF(H104<=I104,"Plan reorder","No action"))))) | T104: =IF(H104<=0,"Out of stock",IF(H104<=I104,"Reorder soon","Healthy")) | U104: Loose leaf tea tin / batch 5
A105: Totals | E105: =SUM(E5:E104) | F105: =SUM(F5:F104) | G105: =SUM(G5:G104) | H105: =SUM(H5:H104) | K105: =SUM(K5:K104) | Q105: =SUM(Q5:Q104)

Sheet Purchases
A1: Purchases
A2: Log restocks and purchase costs. Quantity drives Inventory on-hand and total cost drives the dashboard.
A4: Date | B4: SKU | C4: Supplier | D4: Qty | E4: Unit Cost | F4: Shipping | G4: Total Cost | H4: Notes
A5: 46025 | B5: SKU-001 | C5: Northstar Wholesale | D5: 2 | E5: 0.95 | F5: 1.8 | G5: =D5*E5+F5 | H5: Restock wave 1
A6: 46025 | B6: SKU-002 | C6: Northstar Wholesale | D6: 3 | E6: 1.12 | F6: 2.15 | G6: =D6*E6+F6 | H6: Restock wave 1
A7: 46025 | B7: SKU-003 | C7: Northstar Wholesale | D7: 4 | E7: 1.29 | F7: 2.5 | G7: =D7*E7+F7 | H7: Restock wave 1
A8: 46025 | B8: SKU-004 | C8: Northstar Wholesale | D8: 5 | E8: 1.46 | F8: 2.85 | G8: =D8*E8+F8 | H8: Restock wave 1
A9: 46025 | B9: SKU-005 | C9: Northstar Wholesale | D9: 6 | E9: 1.63 | F9: 3.2 | G9: =D9*E9+F9 | H9: Restock wave 1
A10: 46025 | B10: SKU-006 | C10: Harbor Supply | D10: 2 | E10: 2.1 | F10: 3.55 | G10: =D10*E10+F10 | H10: Restock wave 1
A11: 46026 | B11: SKU-007 | C11: Harbor Supply | D11: 3 | E11: 2.27 | F11: 3.9 | G11: =D11*E11+F11 | H11: Restock wave 1
A12: 46026 | B12: SKU-008 | C12: Harbor Supply | D12: 4 | E12: 2.44 | F12: 1.8 | G12: =D12*E12+F12 | H12: Restock wave 1
A13: 46026 | B13: SKU-009 | C13: Harbor Supply | D13: 5 | E13: 2.61 | F13: 2.15 | G13: =D13*E13+F13 | H13: Restock wave 1
A14: 46026 | B14: SKU-010 | C14: Harbor Supply | D14: 6 | E14: 2.78 | F14: 2.5 | G14: =D14*E14+F14 | H14: Restock wave 1
A15: 46026 | B15: SKU-011 | C15: Paper Trail Co. | D15: 2 | E15: 1.25 | F15: 2.85 | G15: =D15*E15+F15 | H15: Restock wave 1
A16: 46026 | B16: SKU-012 | C16: Paper Trail Co. | D16: 3 | E16: 1.42 | F16: 3.2 | G16: =D16*E16+F16 | H16: Restock wave 1
... A304: 46074 | B304: SKU-100 | C304: Harbor Supply | D304: 6 | E304: 2.87 | F304: 3.91 | G304: =D304*E304+F304 | H304: Restock wave 3
A305: Totals | D305: =SUM(D5:D304) | G305: =SUM(G5:G304)

Sheet Sales
A1: Sales
A2: Log sales orders and see revenue, fees, cost of goods sold, and gross profit.
A4: Date | B4: SKU | C4: Channel | D4: Qty | E4: Unit Price | F4: Fees | G4: Revenue | H4: COGS | I4: Gross Profit | J4: Notes
A5: 46026 | B5: SKU-001 | C5: Etsy | D5: 4 | E5: 2.66 | F5: 0.35 | G5: =D5*E5 | H5: =D5*VLOOKUP(B5,Inventory!$A$5:$J$104,10,FALSE) | I5: =G5-F5-H5 | J5: Order batch 1
A6: 46026 | B6: SKU-002 | C6: Shop | D6: 5 | E6: 3.23 | F6: 0.42 | G6: =D6*E6 | H6: =D6*VLOOKUP(B6,Inventory!$A$5:$J$104,10,FALSE) | I6: =G6-F6-H6 | J6: Order batch 1
A7: 46026 | B7: SKU-003 | C7: Market | D7: 4 | E7: 3.82 | F7: 0.5 | G7: =D7*E7 | H7: =D7*VLOOKUP(B7,Inventory!$A$5:$J$104,10,FALSE) | I7: =G7-F7-H7 | J7: Order batch 1
A8: 46026 | B8: SKU-004 | C8: Retail | D8: 5 | E8: 4.44 | F8: 0.58 | G8: =D8*E8 | H8: =D8*VLOOKUP(B8,Inventory!$A$5:$J$104,10,FALSE) | I8: =G8-F8-H8 | J8: Order batch 1
A9: 46026 | B9: SKU-005 | C9: Wholesale | D9: 3 | E9: 5.09 | F9: 0.66 | G9: =D9*E9 | H9: =D9*VLOOKUP(B9,Inventory!$A$5:$J$104,10,FALSE) | I9: =G9-F9-H9 | J9: Order batch 1
A10: 46027 | B10: SKU-006 | C10: Etsy | D10: 4 | E10: 6.72 | F10: 0.87 | G10: =D10*E10 | H10: =D10*VLOOKUP(B10,Inventory!$A$5:$J$104,10,FALSE) | I10: =G10-F10-H10 | J10: Order batch 1
A11: 46027 | B11: SKU-007 | C11: Shop | D11: 3 | E11: 6.36 | F11: 0.83 | G11: =D11*E11 | H11: =D11*VLOOKUP(B11,Inventory!$A$5:$J$104,10,FALSE) | I11: =G11-F11-H11 | J11: Order batch 1
A12: 46027 | B12: SKU-008 | C12: Market | D12: 4 | E12: 7.03 | F12: 0.91 | G12: =D12*E12 | H12: =D12*VLOOKUP(B12,Inventory!$A$5:$J$104,10,FALSE) | I12: =G12-F12-H12 | J12: Order batch 1
A13: 46027 | B13: SKU-009 | C13: Retail | D13: 3 | E13: 7.73 | F13: 1 | G13: =D13*E13 | H13: =D13*VLOOKUP(B13,Inventory!$A$5:$J$104,10,FALSE) | I13: =G13-F13-H13 | J13: Order batch 1
A14: 46027 | B14: SKU-010 | C14: Wholesale | D14: 4 | E14: 8.45 | F14: 1.1 | G14: =D14*E14 | H14: =D14*VLOOKUP(B14,Inventory!$A$5:$J$104,10,FALSE) | I14: =G14-F14-H14 | J14: Order batch 1
A15: 46028 | B15: SKU-011 | C15: Etsy | D15: 2 | E15: 3.9 | F15: 0.51 | G15: =D15*E15 | H15: =D15*VLOOKUP(B15,Inventory!$A$5:$J$104,10,FALSE) | I15: =G15-F15-H15 | J15: Order batch 1
A16: 46028 | B16: SKU-012 | C16: Shop | D16: 3 | E16: 4.54 | F16: 0.59 | G16: =D16*E16 | H16: =D16*VLOOKUP(B16,Inventory!$A$5:$J$104,10,FALSE) | I16: =G16-F16-H16 | J16: Order batch 1
... A504: 46125 | B504: SKU-100 | C504: Wholesale | D504: 2 | E504: 8.27 | F504: 1.08 | G504: =D504*E504 | H504: =D504*VLOOKUP(B504,Inventory!$A$5:$J$104,10,FALSE) | I504: =G504-F504-H504 | J504: Order batch 5
A505: Totals | D505: =SUM(D5:D504) | G505: =SUM(G5:G504) | H505: =SUM(H5:H504) | I505: =SUM(I5:I504)

Sheet Price Calculator
A1: Price Calculator
A2: Test sale price, expected profit, and margin before you list a product.
A4: Product | B4: SKU | C4: COGS | D4: Packaging | E4: Labor | F4: Overhead | G4: Fee % | H4: Tax % | I4: Target Margin | J4: Suggested Price | K4: Profit | L4: Margin | M4: Notes
A5: Canvas Tote - Sand | B5: SKU-001 | C5: =VLOOKUP(B5,Inventory!$A$5:$J$104,10,FALSE) | D5: 0.18 | E5: 0.44 | F5: 0.25 | G5: 0.13 | H5: 0.1 | I5: 0.42 | J5: =IF(A5="","",ROUND((C5+D5+E5+F5)/(1-(G5+H5+I5)),2)) | K5: =IF(J5="","",J5-(C5+D5+E5+F5)-(J5*G5)-(J5*H5)) | L5: =IF(J5="","",IF(J5=0,"",K5/J5)) | M5: Pricing scenario 1
A6: Canvas Tote - Olive | B6: SKU-002 | C6: =VLOOKUP(B6,Inventory!$A$5:$J$104,10,FALSE) | D6: 0.25 | E6: 0.53 | F6: 0.25 | G6: 0.13 | H6: 0.1 | I6: 0.45 | J6: =IF(A6="","",ROUND((C6+D6+E6+F6)/(1-(G6+H6+I6)),2)) | K6: =IF(J6="","",J6-(C6+D6+E6+F6)-(J6*G6)-(J6*H6)) | L6: =IF(J6="","",IF(J6=0,"",K6/J6)) | M6: Pricing scenario 2
A7: Canvas Tote - Slate | B7: SKU-003 | C7: =VLOOKUP(B7,Inventory!$A$5:$J$104,10,FALSE) | D7: 0.32 | E7: 0.62 | F7: 0.25 | G7: 0.13 | H7: 0.1 | I7: 0.48 | J7: =IF(A7="","",ROUND((C7+D7+E7+F7)/(1-(G7+H7+I7)),2)) | K7: =IF(J7="","",J7-(C7+D7+E7+F7)-(J7*G7)-(J7*H7)) | L7: =IF(J7="","",IF(J7=0,"",K7/J7)) | M7: Pricing scenario 3
A8: Canvas Tote - Coral | B8: SKU-004 | C8: =VLOOKUP(B8,Inventory!$A$5:$J$104,10,FALSE) | D8: 0.39 | E8: 0.71 | F8: 0.25 | G8: 0.13 | H8: 0.1 | I8: 0.42 | J8: =IF(A8="","",ROUND((C8+D8+E8+F8)/(1-(G8+H8+I8)),2)) | K8: =IF(J8="","",J8-(C8+D8+E8+F8)-(J8*G8)-(J8*H8)) | L8: =IF(J8="","",IF(J8=0,"",K8/J8)) | M8: Pricing scenario 4
A9: Canvas Tote - Natural | B9: SKU-005 | C9: =VLOOKUP(B9,Inventory!$A$5:$J$104,10,FALSE) | D9: 0.18 | E9: 0.8 | F9: 0.25 | G9: 0.13 | H9: 0.1 | I9: 0.45 | J9: =IF(A9="","",ROUND((C9+D9+E9+F9)/(1-(G9+H9+I9)),2)) | K9: =IF(J9="","",J9-(C9+D9+E9+F9)-(J9*G9)-(J9*H9)) | L9: =IF(J9="","",IF(J9=0,"",K9/J9)) | M9: Pricing scenario 5
A10: Ceramic Mug - Sand | B10: SKU-006 | C10: =VLOOKUP(B10,Inventory!$A$5:$J$104,10,FALSE) | D10: 0.25 | E10: 0.44 | F10: 0.25 | G10: 0.13 | H10: 0.1 | I10: 0.48 | J10: =IF(A10="","",ROUND((C10+D10+E10+F10)/(1-(G10+H10+I10)),2)) | K10: =IF(J10="","",J10-(C10+D10+E10+F10)-(J10*G10)-(J10*H10)) | L10: =IF(J10="","",IF(J10=0,"",K10/J10)) | M10: Pricing scenario 6
A11: Ceramic Mug - Olive | B11: SKU-007 | C11: =VLOOKUP(B11,Inventory!$A$5:$J$104,10,FALSE) | D11: 0.32 | E11: 0.53 | F11: 0.25 | G11: 0.13 | H11: 0.1 | I11: 0.42 | J11: =IF(A11="","",ROUND((C11+D11+E11+F11)/(1-(G11+H11+I11)),2)) | K11: =IF(J11="","",J11-(C11+D11+E11+F11)-(J11*G11)-(J11*H11)) | L11: =IF(J11="","",IF(J11=0,"",K11/J11)) | M11: Pricing scenario 7
A12: Ceramic Mug - Slate | B12: SKU-008 | C12: =VLOOKUP(B12,Inventory!$A$5:$J$104,10,FALSE) | D12: 0.39 | E12: 0.62 | F12: 0.25 | G12: 0.13 | H12: 0.1 | I12: 0.45 | J12: =IF(A12="","",ROUND((C12+D12+E12+F12)/(1-(G12+H12+I12)),2)) | K12: =IF(J12="","",J12-(C12+D12+E12+F12)-(J12*G12)-(J12*H12)) | L12: =IF(J12="","",IF(J12=0,"",K12/J12)) | M12: Pricing scenario 8
A13: Ceramic Mug - Coral | B13: SKU-009 | C13: =VLOOKUP(B13,Inventory!$A$5:$J$104,10,FALSE) | D13: 0.18 | E13: 0.71 | F13: 0.25 | G13: 0.13 | H13: 0.1 | I13: 0.48 | J13: =IF(A13="","",ROUND((C13+D13+E13+F13)/(1-(G13+H13+I13)),2)) | K13: =IF(J13="","",J13-(C13+D13+E13+F13)-(J13*G13)-(J13*H13)) | L13: =IF(J13="","",IF(J13=0,"",K13/J13)) | M13: Pricing scenario 9
A14: Ceramic Mug - Natural | B14: SKU-010 | C14: =VLOOKUP(B14,Inventory!$A$5:$J$104,10,FALSE) | D14: 0.25 | E14: 0.8 | F14: 0.25 | G14: 0.13 | H14: 0.1 | I14: 0.42 | J14: =IF(A14="","",ROUND((C14+D14+E14+F14)/(1-(G14+H14+I14)),2)) | K14: =IF(J14="","",J14-(C14+D14+E14+F14)-(J14*G14)-(J14*H14)) | L14: =IF(J14="","",IF(J14=0,"",K14/J14)) | M14: Pricing scenario 10
A15: A5 Notebook - Sand | B15: SKU-011 | C15: =VLOOKUP(B15,Inventory!$A$5:$J$104,10,FALSE) | D15: 0.32 | E15: 0.44 | F15: 0.25 | G15: 0.13 | H15: 0.1 | I15: 0.45 | J15: =IF(A15="","",ROUND((C15+D15+E15+F15)/(1-(G15+H15+I15)),2)) | K15: =IF(J15="","",J15-(C15+D15+E15+F15)-(J15*G15)-(J15*H15)) | L15: =IF(J15="","",IF(J15=0,"",K15/J15)) | M15: Pricing scenario 11
A16: A5 Notebook - Olive | B16: SKU-012 | C16: =VLOOKUP(B16,Inventory!$A$5:$J$104,10,FALSE) | D16: 0.39 | E16: 0.53 | F16: 0.25 | G16: 0.13 | H16: 0.1 | I16: 0.48 | J16: =IF(A16="","",ROUND((C16+D16+E16+F16)/(1-(G16+H16+I16)),2)) | K16: =IF(J16="","",J16-(C16+D16+E16+F16)-(J16*G16)-(J16*H16)) | L16: =IF(J16="","",IF(J16=0,"",K16/J16)) | M16: Pricing scenario 12
... A104: Tea Tin - Natural | B104: SKU-100 | C104: =VLOOKUP(B104,Inventory!$A$5:$J$104,10,FALSE) | D104: 0.39 | E104: 0.8 | F104: 0.25 | G104: 0.13 | H104: 0.1 | I104: 0.42 | J104: =IF(A104="","",ROUND((C104+D104+E104+F104)/(1-(G104+H104+I104)),2)) | K104: =IF(J104="","",J104-(C104+D104+E104+F104)-(J104*G104)-(J104*H104)) | L104: =IF(J104="","",IF(J104=0,"",K104/J104)) | M104: Pricing scenario 100

Sheet Price List
A1: Price List
A2: Save approved price snapshots here. The top row mirrors the calculator output for quick reuse.
A4: Date | B4: SKU | C4: Product | D4: Cost | E4: Suggested Price | F4: Profit | G4: Margin | H4: Status | I4: Notes
A5: 46042 | B5: SKU-001 | C5: Canvas Tote - Sand | D5: =VLOOKUP(B5,Inventory!$A$5:$J$104,10,FALSE) | E5: ='Price Calculator'!J5 | F5: ='Price Calculator'!K5 | G5: ='Price Calculator'!L5 | H5: =IF(G5>=0.45,"Good margin","Review") | I5: Pricing scenario 1
A6: 46043 | B6: SKU-002 | C6: Canvas Tote - Olive | D6: =VLOOKUP(B6,Inventory!$A$5:$J$104,10,FALSE) | E6: ='Price Calculator'!J6 | F6: ='Price Calculator'!K6 | G6: ='Price Calculator'!L6 | H6: =IF(G6>=0.45,"Good margin","Review") | I6: Pricing scenario 2
A7: 46044 | B7: SKU-003 | C7: Canvas Tote - Slate | D7: =VLOOKUP(B7,Inventory!$A$5:$J$104,10,FALSE) | E7: ='Price Calculator'!J7 | F7: ='Price Calculator'!K7 | G7: ='Price Calculator'!L7 | H7: =IF(G7>=0.45,"Good margin","Review") | I7: Pricing scenario 3
A8: 46045 | B8: SKU-004 | C8: Canvas Tote - Coral | D8: =VLOOKUP(B8,Inventory!$A$5:$J$104,10,FALSE) | E8: ='Price Calculator'!J8 | F8: ='Price Calculator'!K8 | G8: ='Price Calculator'!L8 | H8: =IF(G8>=0.45,"Good margin","Review") | I8: Pricing scenario 4
A9: 46046 | B9: SKU-005 | C9: Canvas Tote - Natural | D9: =VLOOKUP(B9,Inventory!$A$5:$J$104,10,FALSE) | E9: ='Price Calculator'!J9 | F9: ='Price Calculator'!K9 | G9: ='Price Calculator'!L9 | H9: =IF(G9>=0.45,"Good margin","Review") | I9: Pricing scenario 5
A10: 46047 | B10: SKU-006 | C10: Ceramic Mug - Sand | D10: =VLOOKUP(B10,Inventory!$A$5:$J$104,10,FALSE) | E10: ='Price Calculator'!J10 | F10: ='Price Calculator'!K10 | G10: ='Price Calculator'!L10 | H10: =IF(G10>=0.45,"Good margin","Review") | I10: Pricing scenario 6
A11: 46048 | B11: SKU-007 | C11: Ceramic Mug - Olive | D11: =VLOOKUP(B11,Inventory!$A$5:$J$104,10,FALSE) | E11: ='Price Calculator'!J11 | F11: ='Price Calculator'!K11 | G11: ='Price Calculator'!L11 | H11: =IF(G11>=0.45,"Good margin","Review") | I11: Pricing scenario 7
A12: 46049 | B12: SKU-008 | C12: Ceramic Mug - Slate | D12: =VLOOKUP(B12,Inventory!$A$5:$J$104,10,FALSE) | E12: ='Price Calculator'!J12 | F12: ='Price Calculator'!K12 | G12: ='Price Calculator'!L12 | H12: =IF(G12>=0.45,"Good margin","Review") | I12: Pricing scenario 8
A13: 46050 | B13: SKU-009 | C13: Ceramic Mug - Coral | D13: =VLOOKUP(B13,Inventory!$A$5:$J$104,10,FALSE) | E13: ='Price Calculator'!J13 | F13: ='Price Calculator'!K13 | G13: ='Price Calculator'!L13 | H13: =IF(G13>=0.45,"Good margin","Review") | I13: Pricing scenario 9
A14: 46051 | B14: SKU-010 | C14: Ceramic Mug - Natural | D14: =VLOOKUP(B14,Inventory!$A$5:$J$104,10,FALSE) | E14: ='Price Calculator'!J14 | F14: ='Price Calculator'!K14 | G14: ='Price Calculator'!L14 | H14: =IF(G14>=0.45,"Good margin","Review") | I14: Pricing scenario 10
A15: 46052 | B15: SKU-011 | C15: A5 Notebook - Sand | D15: =VLOOKUP(B15,Inventory!$A$5:$J$104,10,FALSE) | E15: ='Price Calculator'!J15 | F15: ='Price Calculator'!K15 | G15: ='Price Calculator'!L15 | H15: =IF(G15>=0.45,"Good margin","Review") | I15: Pricing scenario 11
A16: 46053 | B16: SKU-012 | C16: A5 Notebook - Olive | D16: =VLOOKUP(B16,Inventory!$A$5:$J$104,10,FALSE) | E16: ='Price Calculator'!J16 | F16: ='Price Calculator'!K16 | G16: ='Price Calculator'!L16 | H16: =IF(G16>=0.45,"Good margin","Review") | I16: Pricing scenario 12
... A104: 46141 | B104: SKU-100 | C104: Tea Tin - Natural | D104: =VLOOKUP(B104,Inventory!$A$5:$J$104,10,FALSE) | E104: ='Price Calculator'!J104 | F104: ='Price Calculator'!K104 | G104: ='Price Calculator'!L104 | H104: =IF(G104>=0.45,"Good margin","Review") | I104: Pricing scenario 100

Sheet Help
A1: Help
A2: Compatibility, limits, and support scope. Keep this sheet visible if you share the file.
A4: Compatible with
A5: • Excel-compatible spreadsheet editors
A6: • Google Sheets standard-formula import
A8: You can change
A9: • Yellow input cells in Setup
A10: • Yellow input cells on Inventory, Purchases, Sales, and Price Calculator
A12: Leave alone
A13: • Dashboard formulas and charts
A14: • Inventory status formulas
A15: • Sales profit formulas
... A24: • Imported protection settings can vary by editor or account.

Sheet Lists
A1: SKUs | B1: Categories
A2: SKU-001 | B2: Accessories
A3: SKU-002 | B3: Drinkware
A4: SKU-003 | B4: Stationery
A5: SKU-004 | B5: Home
A6: SKU-005 | B6: Wall Art
A7: SKU-006 | B7: Apparel
A8: SKU-007
A9: SKU-008
A10: SKU-009
A11: SKU-010
A12: SKU-011
A13: SKU-012
A14: SKU-013
A15: SKU-014
A16: SKU-015
A17: SKU-016
A18: SKU-017
A19: SKU-018
... A101: SKU-100
