Workbook

Sheet Start Here
A1: Inventory Tracker Studio
A2: Example review date is March 15. The seed sales are from the prior 30 days so Inventory can show real reorder behavior.
A4: How the example works | D4: Editable areas
A5: 1. Setup reviews inventory on March 15 and looks back 30 days. | D5: Setup input cells
A6: 2. Sales contains recent February and March example orders for the seeded SKUs. | D6: Blank Inventory SKU, item, supplier, opening stock, unit cost, and notes rows
A7: 3. Inventory uses those sales to calculate velocity, days cover, projected stockout, reorder-by date, and suggested quantity. | D7: Blank Purchase log rows
A8: 4. Read Inventory for the next action: fix stock data, order now, order this week, plan reorder, or no action. | D8: Blank Sales log rows
A9: 5. Once you understand the example, replace the seed rows with your own SKUs, purchases, and last 30 days of sales. | D9: Blank Price Calculator rows
D11: Leave alone
D12: Dashboard formulas and charts
A13: When the workbook gets full | D13: Inventory status formulas
A14: Make a fresh copy, bring over your Inventory list and the last 30 days of Sales, then continue tracking there. | D14: Sales profit formulas
D15: Price List snapshot formulas
A16: What this is not
A17: • Not a subscription app | D17: Seed and working capacity
A18: • Not bank-connected | D18: Seed rows show a real 30-day sales example. Blank rows are ready for your data while formulas cover 100 inventory rows, 300 purchases, 500 sales, 100 calculator rows, and 100 price-list rows.
A19: • Not tax or accounting advice
A20: • Not a live inventory service

Sheet Dashboard
A1: Dashboard
A2: The replenishment decision surface: what to reorder, when, and how much.
B4: Seed SKUs | D4: Order now | F4: Order qty | H4: Inventory value | J4: Purchase spend | L4: Sales revenue | N4: Gross profit
B5: =COUNTA(Inventory!A5:A104) | D5: =COUNTIF(Inventory!S5:S104,"Order now") | F5: =SUM(Inventory!Q5:Q104) | H5: =SUM(Inventory!K5:K104) | J5: =SUM(Purchases!G5:G304) | L5: =SUM(Sales!G5:G504) | N5: =SUM(Sales!I5:I504)
A8: Reorder action mix
A9: Status | B9: Count
A10: Fix stock data | B10: =COUNTIF(Inventory!S5:S104,"Fix stock data")
A11: Order now | B11: =COUNTIF(Inventory!S5:S104,"Order now")
A12: Order this week | B12: =COUNTIF(Inventory!S5:S104,"Order this week")
A13: Plan reorder | B13: =COUNTIF(Inventory!S5:S104,"Plan reorder")
A14: No action | B14: =COUNTIF(Inventory!S5:S104,"No action")
A16: Top notes
A17: • Use Setup first, then Inventory.
A18: • Inventory outputs action, dates, quantity, velocity, derived reorder point, lead time, and safety stock.
A19: • Rows after the seed examples are blank for buyer use but keep formulas and validation.
A20: • If sales exceed available stock, action changes to Fix stock data before any reorder advice.
A21: • Price Calculator helps you test margins before listing.
A22: • Price List stores the approved price snapshot.

Sheet Setup
A1: Setup
A2: Choose the defaults that drive replenishment, stock, and pricing formulas.
A4: Currency symbol | B4: $ | D4: Categories
A5: Review date | B5: 46096 | D5: Accessories, Drinkware, Stationery, Home, Wall Art, Apparel
A6: Sales lookback days | B6: 30
A7: Sales tax | B7: 0.1 | D7: Editable cells
A8: Marketplace fee | B8: 0.13 | D8: Yellow input cells in Setup, Inventory, Purchases, Sales, and Price Calculator.
A9: Target margin | B9: 0.45
A10: Reorder point policy | B10: Derived from velocity, lead time, and safety stock
A11: Lead time days | B11: 14
A12: Safety stock days | B12: 7
A13: Default pack size | B13: 6 | D13: Workbook capacity
A14: Support note | B14: Use the workbook for stock, purchases, sales, and pricing. | D14: The delivered workbook ships with a few seed examples plus blank formula-ready rows: 100 inventory rows, 300 purchase rows, 500 sales rows, 100 calculator rows, and 100 price-list rows.
D16: Unsupported
D17: Live bank sync, tax filing, and custom bookkeeping.

Sheet Inventory
A1: Inventory
A2: Decide what to reorder, when to reorder it, and how much to buy.
A4: SKU | B4: Item | C4: Category | D4: Supplier | E4: Opening Stock | F4: Purchases | G4: Sales | H4: On Hand | I4: Derived Reorder Point | J4: Unit Cost | K4: Inventory Value | L4: Sales Velocity/Day | M4: Days Cover | N4: Projected Stockout | O4: Lead Time Used | P4: Safety Stock | Q4: Suggested Order Qty | R4: Reorder By | S4: Reorder Action | T4: Status | U4: Notes
A5: SKU-001 | B5: Canvas Tote - Sand | C5: Accessories | D5: Northstar Wholesale | E5: 24 | F5: =IF($A5="","",SUMIFS(Purchases!$D$5:$D$304,Purchases!$B$5:$B$304,$A5)) | G5: =IF($A5="","",SUMIFS(Sales!$D$5:$D$504,Sales!$B$5:$B$504,$A5)) | H5: =IF($A5="","",MAX(0,(E5+F5-G5))) | I5: =IF($A5="","",ROUNDUP(L5*O5+P5,0)) | J5: 0.95 | K5: =IF($A5="","",H5*J5) | L5: =IF($A5="","",IFERROR(SUMIFS(Sales!$D$5:$D$504,Sales!$B$5:$B$504,$A5,Sales!$A$5:$A$504,">="&Setup!$B$5-Setup!$B$6,Sales!$A$5:$A$504,"<="&Setup!$B$5)/Setup!$B$6,0)) | M5: =IF($A5="","",IF(L5<=0,999,H5/L5)) | N5: =IF($A5="","",IF(L5<=0,"No recent sales",Setup!$B$5+M5)) | O5: =IF($A5="","",Setup!$B$11) | P5: =IF($A5="","",ROUNDUP(L5*Setup!$B$12,0)) | Q5: =IF($A5="","",IF((E5+F5-G5)<0,0,IF(MAX(0,ROUNDUP(I5-H5,0))=0,0,CEILING(MAX(0,ROUNDUP(I5-H5,0)),Setup!$B$13)))) | R5: =IF($A5="","",IF(L5<=0,"No sales signal",N5-O5)) | S5: =IF($A5="","",IF((E5+F5-G5)<0,"Fix stock data",IF(R5="No sales signal","No action",IF(R5<=Setup!$B$5,"Order now",IF(R5<=Setup!$B$5+7,"Order this week",IF(H5<=I5,"Plan reorder","No action")))))) | T5: =IF($A5="","",IF((E5+F5-G5)<0,"Review stock data",IF(H5=0,"Out of stock",IF(H5<=I5,"Reorder soon","Healthy")))) | U5: Reusable carry tote / batch 1
A6: SKU-002 | B6: Canvas Tote - Olive | C6: Accessories | D6: Northstar Wholesale | E6: 27 | F6: =IF($A6="","",SUMIFS(Purchases!$D$5:$D$304,Purchases!$B$5:$B$304,$A6)) | G6: =IF($A6="","",SUMIFS(Sales!$D$5:$D$504,Sales!$B$5:$B$504,$A6)) | H6: =IF($A6="","",MAX(0,(E6+F6-G6))) | I6: =IF($A6="","",ROUNDUP(L6*O6+P6,0)) | J6: 1.12 | K6: =IF($A6="","",H6*J6) | L6: =IF($A6="","",IFERROR(SUMIFS(Sales!$D$5:$D$504,Sales!$B$5:$B$504,$A6,Sales!$A$5:$A$504,">="&Setup!$B$5-Setup!$B$6,Sales!$A$5:$A$504,"<="&Setup!$B$5)/Setup!$B$6,0)) | M6: =IF($A6="","",IF(L6<=0,999,H6/L6)) | N6: =IF($A6="","",IF(L6<=0,"No recent sales",Setup!$B$5+M6)) | O6: =IF($A6="","",Setup!$B$11) | P6: =IF($A6="","",ROUNDUP(L6*Setup!$B$12,0)) | Q6: =IF($A6="","",IF((E6+F6-G6)<0,0,IF(MAX(0,ROUNDUP(I6-H6,0))=0,0,CEILING(MAX(0,ROUNDUP(I6-H6,0)),Setup!$B$13)))) | R6: =IF($A6="","",IF(L6<=0,"No sales signal",N6-O6)) | S6: =IF($A6="","",IF((E6+F6-G6)<0,"Fix stock data",IF(R6="No sales signal","No action",IF(R6<=Setup!$B$5,"Order now",IF(R6<=Setup!$B$5+7,"Order this week",IF(H6<=I6,"Plan reorder","No action")))))) | T6: =IF($A6="","",IF((E6+F6-G6)<0,"Review stock data",IF(H6=0,"Out of stock",IF(H6<=I6,"Reorder soon","Healthy")))) | U6: Reusable carry tote / batch 1
A7: SKU-003 | B7: Canvas Tote - Slate | C7: Accessories | D7: Northstar Wholesale | E7: 24 | F7: =IF($A7="","",SUMIFS(Purchases!$D$5:$D$304,Purchases!$B$5:$B$304,$A7)) | G7: =IF($A7="","",SUMIFS(Sales!$D$5:$D$504,Sales!$B$5:$B$504,$A7)) | H7: =IF($A7="","",MAX(0,(E7+F7-G7))) | I7: =IF($A7="","",ROUNDUP(L7*O7+P7,0)) | J7: 1.29 | K7: =IF($A7="","",H7*J7) | L7: =IF($A7="","",IFERROR(SUMIFS(Sales!$D$5:$D$504,Sales!$B$5:$B$504,$A7,Sales!$A$5:$A$504,">="&Setup!$B$5-Setup!$B$6,Sales!$A$5:$A$504,"<="&Setup!$B$5)/Setup!$B$6,0)) | M7: =IF($A7="","",IF(L7<=0,999,H7/L7)) | N7: =IF($A7="","",IF(L7<=0,"No recent sales",Setup!$B$5+M7)) | O7: =IF($A7="","",Setup!$B$11) | P7: =IF($A7="","",ROUNDUP(L7*Setup!$B$12,0)) | Q7: =IF($A7="","",IF((E7+F7-G7)<0,0,IF(MAX(0,ROUNDUP(I7-H7,0))=0,0,CEILING(MAX(0,ROUNDUP(I7-H7,0)),Setup!$B$13)))) | R7: =IF($A7="","",IF(L7<=0,"No sales signal",N7-O7)) | S7: =IF($A7="","",IF((E7+F7-G7)<0,"Fix stock data",IF(R7="No sales signal","No action",IF(R7<=Setup!$B$5,"Order now",IF(R7<=Setup!$B$5+7,"Order this week",IF(H7<=I7,"Plan reorder","No action")))))) | T7: =IF($A7="","",IF((E7+F7-G7)<0,"Review stock data",IF(H7=0,"Out of stock",IF(H7<=I7,"Reorder soon","Healthy")))) | U7: Reusable carry tote / batch 1
A8: SKU-004 | B8: Canvas Tote - Coral | C8: Accessories | D8: Northstar Wholesale | E8: 27 | F8: =IF($A8="","",SUMIFS(Purchases!$D$5:$D$304,Purchases!$B$5:$B$304,$A8)) | G8: =IF($A8="","",SUMIFS(Sales!$D$5:$D$504,Sales!$B$5:$B$504,$A8)) | H8: =IF($A8="","",MAX(0,(E8+F8-G8))) | I8: =IF($A8="","",ROUNDUP(L8*O8+P8,0)) | J8: 1.46 | K8: =IF($A8="","",H8*J8) | L8: =IF($A8="","",IFERROR(SUMIFS(Sales!$D$5:$D$504,Sales!$B$5:$B$504,$A8,Sales!$A$5:$A$504,">="&Setup!$B$5-Setup!$B$6,Sales!$A$5:$A$504,"<="&Setup!$B$5)/Setup!$B$6,0)) | M8: =IF($A8="","",IF(L8<=0,999,H8/L8)) | N8: =IF($A8="","",IF(L8<=0,"No recent sales",Setup!$B$5+M8)) | O8: =IF($A8="","",Setup!$B$11) | P8: =IF($A8="","",ROUNDUP(L8*Setup!$B$12,0)) | Q8: =IF($A8="","",IF((E8+F8-G8)<0,0,IF(MAX(0,ROUNDUP(I8-H8,0))=0,0,CEILING(MAX(0,ROUNDUP(I8-H8,0)),Setup!$B$13)))) | R8: =IF($A8="","",IF(L8<=0,"No sales signal",N8-O8)) | S8: =IF($A8="","",IF((E8+F8-G8)<0,"Fix stock data",IF(R8="No sales signal","No action",IF(R8<=Setup!$B$5,"Order now",IF(R8<=Setup!$B$5+7,"Order this week",IF(H8<=I8,"Plan reorder","No action")))))) | T8: =IF($A8="","",IF((E8+F8-G8)<0,"Review stock data",IF(H8=0,"Out of stock",IF(H8<=I8,"Reorder soon","Healthy")))) | U8: Reusable carry tote / batch 1
A9: SKU-005 | B9: Canvas Tote - Natural | C9: Accessories | D9: Northstar Wholesale | E9: 30 | F9: =IF($A9="","",SUMIFS(Purchases!$D$5:$D$304,Purchases!$B$5:$B$304,$A9)) | G9: =IF($A9="","",SUMIFS(Sales!$D$5:$D$504,Sales!$B$5:$B$504,$A9)) | H9: =IF($A9="","",MAX(0,(E9+F9-G9))) | I9: =IF($A9="","",ROUNDUP(L9*O9+P9,0)) | J9: 1.63 | K9: =IF($A9="","",H9*J9) | L9: =IF($A9="","",IFERROR(SUMIFS(Sales!$D$5:$D$504,Sales!$B$5:$B$504,$A9,Sales!$A$5:$A$504,">="&Setup!$B$5-Setup!$B$6,Sales!$A$5:$A$504,"<="&Setup!$B$5)/Setup!$B$6,0)) | M9: =IF($A9="","",IF(L9<=0,999,H9/L9)) | N9: =IF($A9="","",IF(L9<=0,"No recent sales",Setup!$B$5+M9)) | O9: =IF($A9="","",Setup!$B$11) | P9: =IF($A9="","",ROUNDUP(L9*Setup!$B$12,0)) | Q9: =IF($A9="","",IF((E9+F9-G9)<0,0,IF(MAX(0,ROUNDUP(I9-H9,0))=0,0,CEILING(MAX(0,ROUNDUP(I9-H9,0)),Setup!$B$13)))) | R9: =IF($A9="","",IF(L9<=0,"No sales signal",N9-O9)) | S9: =IF($A9="","",IF((E9+F9-G9)<0,"Fix stock data",IF(R9="No sales signal","No action",IF(R9<=Setup!$B$5,"Order now",IF(R9<=Setup!$B$5+7,"Order this week",IF(H9<=I9,"Plan reorder","No action")))))) | T9: =IF($A9="","",IF((E9+F9-G9)<0,"Review stock data",IF(H9=0,"Out of stock",IF(H9<=I9,"Reorder soon","Healthy")))) | U9: Reusable carry tote / batch 1
A10: SKU-006 | B10: Ceramic Mug - Sand | C10: Drinkware | D10: Harbor Supply | E10: 32 | F10: =IF($A10="","",SUMIFS(Purchases!$D$5:$D$304,Purchases!$B$5:$B$304,$A10)) | G10: =IF($A10="","",SUMIFS(Sales!$D$5:$D$504,Sales!$B$5:$B$504,$A10)) | H10: =IF($A10="","",MAX(0,(E10+F10-G10))) | I10: =IF($A10="","",ROUNDUP(L10*O10+P10,0)) | J10: 2.1 | K10: =IF($A10="","",H10*J10) | L10: =IF($A10="","",IFERROR(SUMIFS(Sales!$D$5:$D$504,Sales!$B$5:$B$504,$A10,Sales!$A$5:$A$504,">="&Setup!$B$5-Setup!$B$6,Sales!$A$5:$A$504,"<="&Setup!$B$5)/Setup!$B$6,0)) | M10: =IF($A10="","",IF(L10<=0,999,H10/L10)) | N10: =IF($A10="","",IF(L10<=0,"No recent sales",Setup!$B$5+M10)) | O10: =IF($A10="","",Setup!$B$11) | P10: =IF($A10="","",ROUNDUP(L10*Setup!$B$12,0)) | Q10: =IF($A10="","",IF((E10+F10-G10)<0,0,IF(MAX(0,ROUNDUP(I10-H10,0))=0,0,CEILING(MAX(0,ROUNDUP(I10-H10,0)),Setup!$B$13)))) | R10: =IF($A10="","",IF(L10<=0,"No sales signal",N10-O10)) | S10: =IF($A10="","",IF((E10+F10-G10)<0,"Fix stock data",IF(R10="No sales signal","No action",IF(R10<=Setup!$B$5,"Order now",IF(R10<=Setup!$B$5+7,"Order this week",IF(H10<=I10,"Plan reorder","No action")))))) | T10: =IF($A10="","",IF((E10+F10-G10)<0,"Review stock data",IF(H10=0,"Out of stock",IF(H10<=I10,"Reorder soon","Healthy")))) | U10: Gloss finish mug / batch 1
A11: SKU-007 | B11: Ceramic Mug - Olive | C11: Drinkware | D11: Harbor Supply | E11: 28 | F11: =IF($A11="","",SUMIFS(Purchases!$D$5:$D$304,Purchases!$B$5:$B$304,$A11)) | G11: =IF($A11="","",SUMIFS(Sales!$D$5:$D$504,Sales!$B$5:$B$504,$A11)) | H11: =IF($A11="","",MAX(0,(E11+F11-G11))) | I11: =IF($A11="","",ROUNDUP(L11*O11+P11,0)) | J11: 2.27 | K11: =IF($A11="","",H11*J11) | L11: =IF($A11="","",IFERROR(SUMIFS(Sales!$D$5:$D$504,Sales!$B$5:$B$504,$A11,Sales!$A$5:$A$504,">="&Setup!$B$5-Setup!$B$6,Sales!$A$5:$A$504,"<="&Setup!$B$5)/Setup!$B$6,0)) | M11: =IF($A11="","",IF(L11<=0,999,H11/L11)) | N11: =IF($A11="","",IF(L11<=0,"No recent sales",Setup!$B$5+M11)) | O11: =IF($A11="","",Setup!$B$11) | P11: =IF($A11="","",ROUNDUP(L11*Setup!$B$12,0)) | Q11: =IF($A11="","",IF((E11+F11-G11)<0,0,IF(MAX(0,ROUNDUP(I11-H11,0))=0,0,CEILING(MAX(0,ROUNDUP(I11-H11,0)),Setup!$B$13)))) | R11: =IF($A11="","",IF(L11<=0,"No sales signal",N11-O11)) | S11: =IF($A11="","",IF((E11+F11-G11)<0,"Fix stock data",IF(R11="No sales signal","No action",IF(R11<=Setup!$B$5,"Order now",IF(R11<=Setup!$B$5+7,"Order this week",IF(H11<=I11,"Plan reorder","No action")))))) | T11: =IF($A11="","",IF((E11+F11-G11)<0,"Review stock data",IF(H11=0,"Out of stock",IF(H11<=I11,"Reorder soon","Healthy")))) | U11: Gloss finish mug / batch 1
A12: SKU-008 | B12: Ceramic Mug - Slate | C12: Drinkware | D12: Harbor Supply | E12: 30 | F12: =IF($A12="","",SUMIFS(Purchases!$D$5:$D$304,Purchases!$B$5:$B$304,$A12)) | G12: =IF($A12="","",SUMIFS(Sales!$D$5:$D$504,Sales!$B$5:$B$504,$A12)) | H12: =IF($A12="","",MAX(0,(E12+F12-G12))) | I12: =IF($A12="","",ROUNDUP(L12*O12+P12,0)) | J12: 2.44 | K12: =IF($A12="","",H12*J12) | L12: =IF($A12="","",IFERROR(SUMIFS(Sales!$D$5:$D$504,Sales!$B$5:$B$504,$A12,Sales!$A$5:$A$504,">="&Setup!$B$5-Setup!$B$6,Sales!$A$5:$A$504,"<="&Setup!$B$5)/Setup!$B$6,0)) | M12: =IF($A12="","",IF(L12<=0,999,H12/L12)) | N12: =IF($A12="","",IF(L12<=0,"No recent sales",Setup!$B$5+M12)) | O12: =IF($A12="","",Setup!$B$11) | P12: =IF($A12="","",ROUNDUP(L12*Setup!$B$12,0)) | Q12: =IF($A12="","",IF((E12+F12-G12)<0,0,IF(MAX(0,ROUNDUP(I12-H12,0))=0,0,CEILING(MAX(0,ROUNDUP(I12-H12,0)),Setup!$B$13)))) | R12: =IF($A12="","",IF(L12<=0,"No sales signal",N12-O12)) | S12: =IF($A12="","",IF((E12+F12-G12)<0,"Fix stock data",IF(R12="No sales signal","No action",IF(R12<=Setup!$B$5,"Order now",IF(R12<=Setup!$B$5+7,"Order this week",IF(H12<=I12,"Plan reorder","No action")))))) | T12: =IF($A12="","",IF((E12+F12-G12)<0,"Review stock data",IF(H12=0,"Out of stock",IF(H12<=I12,"Reorder soon","Healthy")))) | U12: Gloss finish mug / batch 1
F13: =IF($A13="","",SUMIFS(Purchases!$D$5:$D$304,Purchases!$B$5:$B$304,$A13)) | G13: =IF($A13="","",SUMIFS(Sales!$D$5:$D$504,Sales!$B$5:$B$504,$A13)) | H13: =IF($A13="","",MAX(0,(E13+F13-G13))) | I13: =IF($A13="","",ROUNDUP(L13*O13+P13,0)) | K13: =IF($A13="","",H13*J13) | L13: =IF($A13="","",IFERROR(SUMIFS(Sales!$D$5:$D$504,Sales!$B$5:$B$504,$A13,Sales!$A$5:$A$504,">="&Setup!$B$5-Setup!$B$6,Sales!$A$5:$A$504,"<="&Setup!$B$5)/Setup!$B$6,0)) | M13: =IF($A13="","",IF(L13<=0,999,H13/L13)) | N13: =IF($A13="","",IF(L13<=0,"No recent sales",Setup!$B$5+M13)) | O13: =IF($A13="","",Setup!$B$11) | P13: =IF($A13="","",ROUNDUP(L13*Setup!$B$12,0)) | Q13: =IF($A13="","",IF((E13+F13-G13)<0,0,IF(MAX(0,ROUNDUP(I13-H13,0))=0,0,CEILING(MAX(0,ROUNDUP(I13-H13,0)),Setup!$B$13)))) | R13: =IF($A13="","",IF(L13<=0,"No sales signal",N13-O13)) | S13: =IF($A13="","",IF((E13+F13-G13)<0,"Fix stock data",IF(R13="No sales signal","No action",IF(R13<=Setup!$B$5,"Order now",IF(R13<=Setup!$B$5+7,"Order this week",IF(H13<=I13,"Plan reorder","No action")))))) | T13: =IF($A13="","",IF((E13+F13-G13)<0,"Review stock data",IF(H13=0,"Out of stock",IF(H13<=I13,"Reorder soon","Healthy"))))
F14: =IF($A14="","",SUMIFS(Purchases!$D$5:$D$304,Purchases!$B$5:$B$304,$A14)) | G14: =IF($A14="","",SUMIFS(Sales!$D$5:$D$504,Sales!$B$5:$B$504,$A14)) | H14: =IF($A14="","",MAX(0,(E14+F14-G14))) | I14: =IF($A14="","",ROUNDUP(L14*O14+P14,0)) | K14: =IF($A14="","",H14*J14) | L14: =IF($A14="","",IFERROR(SUMIFS(Sales!$D$5:$D$504,Sales!$B$5:$B$504,$A14,Sales!$A$5:$A$504,">="&Setup!$B$5-Setup!$B$6,Sales!$A$5:$A$504,"<="&Setup!$B$5)/Setup!$B$6,0)) | M14: =IF($A14="","",IF(L14<=0,999,H14/L14)) | N14: =IF($A14="","",IF(L14<=0,"No recent sales",Setup!$B$5+M14)) | O14: =IF($A14="","",Setup!$B$11) | P14: =IF($A14="","",ROUNDUP(L14*Setup!$B$12,0)) | Q14: =IF($A14="","",IF((E14+F14-G14)<0,0,IF(MAX(0,ROUNDUP(I14-H14,0))=0,0,CEILING(MAX(0,ROUNDUP(I14-H14,0)),Setup!$B$13)))) | R14: =IF($A14="","",IF(L14<=0,"No sales signal",N14-O14)) | S14: =IF($A14="","",IF((E14+F14-G14)<0,"Fix stock data",IF(R14="No sales signal","No action",IF(R14<=Setup!$B$5,"Order now",IF(R14<=Setup!$B$5+7,"Order this week",IF(H14<=I14,"Plan reorder","No action")))))) | T14: =IF($A14="","",IF((E14+F14-G14)<0,"Review stock data",IF(H14=0,"Out of stock",IF(H14<=I14,"Reorder soon","Healthy"))))
F15: =IF($A15="","",SUMIFS(Purchases!$D$5:$D$304,Purchases!$B$5:$B$304,$A15)) | G15: =IF($A15="","",SUMIFS(Sales!$D$5:$D$504,Sales!$B$5:$B$504,$A15)) | H15: =IF($A15="","",MAX(0,(E15+F15-G15))) | I15: =IF($A15="","",ROUNDUP(L15*O15+P15,0)) | K15: =IF($A15="","",H15*J15) | L15: =IF($A15="","",IFERROR(SUMIFS(Sales!$D$5:$D$504,Sales!$B$5:$B$504,$A15,Sales!$A$5:$A$504,">="&Setup!$B$5-Setup!$B$6,Sales!$A$5:$A$504,"<="&Setup!$B$5)/Setup!$B$6,0)) | M15: =IF($A15="","",IF(L15<=0,999,H15/L15)) | N15: =IF($A15="","",IF(L15<=0,"No recent sales",Setup!$B$5+M15)) | O15: =IF($A15="","",Setup!$B$11) | P15: =IF($A15="","",ROUNDUP(L15*Setup!$B$12,0)) | Q15: =IF($A15="","",IF((E15+F15-G15)<0,0,IF(MAX(0,ROUNDUP(I15-H15,0))=0,0,CEILING(MAX(0,ROUNDUP(I15-H15,0)),Setup!$B$13)))) | R15: =IF($A15="","",IF(L15<=0,"No sales signal",N15-O15)) | S15: =IF($A15="","",IF((E15+F15-G15)<0,"Fix stock data",IF(R15="No sales signal","No action",IF(R15<=Setup!$B$5,"Order now",IF(R15<=Setup!$B$5+7,"Order this week",IF(H15<=I15,"Plan reorder","No action")))))) | T15: =IF($A15="","",IF((E15+F15-G15)<0,"Review stock data",IF(H15=0,"Out of stock",IF(H15<=I15,"Reorder soon","Healthy"))))
F16: =IF($A16="","",SUMIFS(Purchases!$D$5:$D$304,Purchases!$B$5:$B$304,$A16)) | G16: =IF($A16="","",SUMIFS(Sales!$D$5:$D$504,Sales!$B$5:$B$504,$A16)) | H16: =IF($A16="","",MAX(0,(E16+F16-G16))) | I16: =IF($A16="","",ROUNDUP(L16*O16+P16,0)) | K16: =IF($A16="","",H16*J16) | L16: =IF($A16="","",IFERROR(SUMIFS(Sales!$D$5:$D$504,Sales!$B$5:$B$504,$A16,Sales!$A$5:$A$504,">="&Setup!$B$5-Setup!$B$6,Sales!$A$5:$A$504,"<="&Setup!$B$5)/Setup!$B$6,0)) | M16: =IF($A16="","",IF(L16<=0,999,H16/L16)) | N16: =IF($A16="","",IF(L16<=0,"No recent sales",Setup!$B$5+M16)) | O16: =IF($A16="","",Setup!$B$11) | P16: =IF($A16="","",ROUNDUP(L16*Setup!$B$12,0)) | Q16: =IF($A16="","",IF((E16+F16-G16)<0,0,IF(MAX(0,ROUNDUP(I16-H16,0))=0,0,CEILING(MAX(0,ROUNDUP(I16-H16,0)),Setup!$B$13)))) | R16: =IF($A16="","",IF(L16<=0,"No sales signal",N16-O16)) | S16: =IF($A16="","",IF((E16+F16-G16)<0,"Fix stock data",IF(R16="No sales signal","No action",IF(R16<=Setup!$B$5,"Order now",IF(R16<=Setup!$B$5+7,"Order this week",IF(H16<=I16,"Plan reorder","No action")))))) | T16: =IF($A16="","",IF((E16+F16-G16)<0,"Review stock data",IF(H16=0,"Out of stock",IF(H16<=I16,"Reorder soon","Healthy"))))
F17: =IF($A17="","",SUMIFS(Purchases!$D$5:$D$304,Purchases!$B$5:$B$304,$A17)) | G17: =IF($A17="","",SUMIFS(Sales!$D$5:$D$504,Sales!$B$5:$B$504,$A17)) | H17: =IF($A17="","",MAX(0,(E17+F17-G17))) | I17: =IF($A17="","",ROUNDUP(L17*O17+P17,0)) | K17: =IF($A17="","",H17*J17) | L17: =IF($A17="","",IFERROR(SUMIFS(Sales!$D$5:$D$504,Sales!$B$5:$B$504,$A17,Sales!$A$5:$A$504,">="&Setup!$B$5-Setup!$B$6,Sales!$A$5:$A$504,"<="&Setup!$B$5)/Setup!$B$6,0)) | M17: =IF($A17="","",IF(L17<=0,999,H17/L17)) | N17: =IF($A17="","",IF(L17<=0,"No recent sales",Setup!$B$5+M17)) | O17: =IF($A17="","",Setup!$B$11) | P17: =IF($A17="","",ROUNDUP(L17*Setup!$B$12,0)) | Q17: =IF($A17="","",IF((E17+F17-G17)<0,0,IF(MAX(0,ROUNDUP(I17-H17,0))=0,0,CEILING(MAX(0,ROUNDUP(I17-H17,0)),Setup!$B$13)))) | R17: =IF($A17="","",IF(L17<=0,"No sales signal",N17-O17)) | S17: =IF($A17="","",IF((E17+F17-G17)<0,"Fix stock data",IF(R17="No sales signal","No action",IF(R17<=Setup!$B$5,"Order now",IF(R17<=Setup!$B$5+7,"Order this week",IF(H17<=I17,"Plan reorder","No action")))))) | T17: =IF($A17="","",IF((E17+F17-G17)<0,"Review stock data",IF(H17=0,"Out of stock",IF(H17<=I17,"Reorder soon","Healthy"))))
F18: =IF($A18="","",SUMIFS(Purchases!$D$5:$D$304,Purchases!$B$5:$B$304,$A18)) | G18: =IF($A18="","",SUMIFS(Sales!$D$5:$D$504,Sales!$B$5:$B$504,$A18)) | H18: =IF($A18="","",MAX(0,(E18+F18-G18))) | I18: =IF($A18="","",ROUNDUP(L18*O18+P18,0)) | K18: =IF($A18="","",H18*J18) | L18: =IF($A18="","",IFERROR(SUMIFS(Sales!$D$5:$D$504,Sales!$B$5:$B$504,$A18,Sales!$A$5:$A$504,">="&Setup!$B$5-Setup!$B$6,Sales!$A$5:$A$504,"<="&Setup!$B$5)/Setup!$B$6,0)) | M18: =IF($A18="","",IF(L18<=0,999,H18/L18)) | N18: =IF($A18="","",IF(L18<=0,"No recent sales",Setup!$B$5+M18)) | O18: =IF($A18="","",Setup!$B$11) | P18: =IF($A18="","",ROUNDUP(L18*Setup!$B$12,0)) | Q18: =IF($A18="","",IF((E18+F18-G18)<0,0,IF(MAX(0,ROUNDUP(I18-H18,0))=0,0,CEILING(MAX(0,ROUNDUP(I18-H18,0)),Setup!$B$13)))) | R18: =IF($A18="","",IF(L18<=0,"No sales signal",N18-O18)) | S18: =IF($A18="","",IF((E18+F18-G18)<0,"Fix stock data",IF(R18="No sales signal","No action",IF(R18<=Setup!$B$5,"Order now",IF(R18<=Setup!$B$5+7,"Order this week",IF(H18<=I18,"Plan reorder","No action")))))) | T18: =IF($A18="","",IF((E18+F18-G18)<0,"Review stock data",IF(H18=0,"Out of stock",IF(H18<=I18,"Reorder soon","Healthy"))))
F19: =IF($A19="","",SUMIFS(Purchases!$D$5:$D$304,Purchases!$B$5:$B$304,$A19)) | G19: =IF($A19="","",SUMIFS(Sales!$D$5:$D$504,Sales!$B$5:$B$504,$A19)) | H19: =IF($A19="","",MAX(0,(E19+F19-G19))) | I19: =IF($A19="","",ROUNDUP(L19*O19+P19,0)) | K19: =IF($A19="","",H19*J19) | L19: =IF($A19="","",IFERROR(SUMIFS(Sales!$D$5:$D$504,Sales!$B$5:$B$504,$A19,Sales!$A$5:$A$504,">="&Setup!$B$5-Setup!$B$6,Sales!$A$5:$A$504,"<="&Setup!$B$5)/Setup!$B$6,0)) | M19: =IF($A19="","",IF(L19<=0,999,H19/L19)) | N19: =IF($A19="","",IF(L19<=0,"No recent sales",Setup!$B$5+M19)) | O19: =IF($A19="","",Setup!$B$11) | P19: =IF($A19="","",ROUNDUP(L19*Setup!$B$12,0)) | Q19: =IF($A19="","",IF((E19+F19-G19)<0,0,IF(MAX(0,ROUNDUP(I19-H19,0))=0,0,CEILING(MAX(0,ROUNDUP(I19-H19,0)),Setup!$B$13)))) | R19: =IF($A19="","",IF(L19<=0,"No sales signal",N19-O19)) | S19: =IF($A19="","",IF((E19+F19-G19)<0,"Fix stock data",IF(R19="No sales signal","No action",IF(R19<=Setup!$B$5,"Order now",IF(R19<=Setup!$B$5+7,"Order this week",IF(H19<=I19,"Plan reorder","No action")))))) | T19: =IF($A19="","",IF((E19+F19-G19)<0,"Review stock data",IF(H19=0,"Out of stock",IF(H19<=I19,"Reorder soon","Healthy"))))
F20: =IF($A20="","",SUMIFS(Purchases!$D$5:$D$304,Purchases!$B$5:$B$304,$A20)) | G20: =IF($A20="","",SUMIFS(Sales!$D$5:$D$504,Sales!$B$5:$B$504,$A20)) | H20: =IF($A20="","",MAX(0,(E20+F20-G20))) | I20: =IF($A20="","",ROUNDUP(L20*O20+P20,0)) | K20: =IF($A20="","",H20*J20) | L20: =IF($A20="","",IFERROR(SUMIFS(Sales!$D$5:$D$504,Sales!$B$5:$B$504,$A20,Sales!$A$5:$A$504,">="&Setup!$B$5-Setup!$B$6,Sales!$A$5:$A$504,"<="&Setup!$B$5)/Setup!$B$6,0)) | M20: =IF($A20="","",IF(L20<=0,999,H20/L20)) | N20: =IF($A20="","",IF(L20<=0,"No recent sales",Setup!$B$5+M20)) | O20: =IF($A20="","",Setup!$B$11) | P20: =IF($A20="","",ROUNDUP(L20*Setup!$B$12,0)) | Q20: =IF($A20="","",IF((E20+F20-G20)<0,0,IF(MAX(0,ROUNDUP(I20-H20,0))=0,0,CEILING(MAX(0,ROUNDUP(I20-H20,0)),Setup!$B$13)))) | R20: =IF($A20="","",IF(L20<=0,"No sales signal",N20-O20)) | S20: =IF($A20="","",IF((E20+F20-G20)<0,"Fix stock data",IF(R20="No sales signal","No action",IF(R20<=Setup!$B$5,"Order now",IF(R20<=Setup!$B$5+7,"Order this week",IF(H20<=I20,"Plan reorder","No action")))))) | T20: =IF($A20="","",IF((E20+F20-G20)<0,"Review stock data",IF(H20=0,"Out of stock",IF(H20<=I20,"Reorder soon","Healthy"))))
F21: =IF($A21="","",SUMIFS(Purchases!$D$5:$D$304,Purchases!$B$5:$B$304,$A21)) | G21: =IF($A21="","",SUMIFS(Sales!$D$5:$D$504,Sales!$B$5:$B$504,$A21)) | H21: =IF($A21="","",MAX(0,(E21+F21-G21))) | I21: =IF($A21="","",ROUNDUP(L21*O21+P21,0)) | K21: =IF($A21="","",H21*J21) | L21: =IF($A21="","",IFERROR(SUMIFS(Sales!$D$5:$D$504,Sales!$B$5:$B$504,$A21,Sales!$A$5:$A$504,">="&Setup!$B$5-Setup!$B$6,Sales!$A$5:$A$504,"<="&Setup!$B$5)/Setup!$B$6,0)) | M21: =IF($A21="","",IF(L21<=0,999,H21/L21)) | N21: =IF($A21="","",IF(L21<=0,"No recent sales",Setup!$B$5+M21)) | O21: =IF($A21="","",Setup!$B$11) | P21: =IF($A21="","",ROUNDUP(L21*Setup!$B$12,0)) | Q21: =IF($A21="","",IF((E21+F21-G21)<0,0,IF(MAX(0,ROUNDUP(I21-H21,0))=0,0,CEILING(MAX(0,ROUNDUP(I21-H21,0)),Setup!$B$13)))) | R21: =IF($A21="","",IF(L21<=0,"No sales signal",N21-O21)) | S21: =IF($A21="","",IF((E21+F21-G21)<0,"Fix stock data",IF(R21="No sales signal","No action",IF(R21<=Setup!$B$5,"Order now",IF(R21<=Setup!$B$5+7,"Order this week",IF(H21<=I21,"Plan reorder","No action")))))) | T21: =IF($A21="","",IF((E21+F21-G21)<0,"Review stock data",IF(H21=0,"Out of stock",IF(H21<=I21,"Reorder soon","Healthy"))))
F22: =IF($A22="","",SUMIFS(Purchases!$D$5:$D$304,Purchases!$B$5:$B$304,$A22)) | G22: =IF($A22="","",SUMIFS(Sales!$D$5:$D$504,Sales!$B$5:$B$504,$A22)) | H22: =IF($A22="","",MAX(0,(E22+F22-G22))) | I22: =IF($A22="","",ROUNDUP(L22*O22+P22,0)) | K22: =IF($A22="","",H22*J22) | L22: =IF($A22="","",IFERROR(SUMIFS(Sales!$D$5:$D$504,Sales!$B$5:$B$504,$A22,Sales!$A$5:$A$504,">="&Setup!$B$5-Setup!$B$6,Sales!$A$5:$A$504,"<="&Setup!$B$5)/Setup!$B$6,0)) | M22: =IF($A22="","",IF(L22<=0,999,H22/L22)) | N22: =IF($A22="","",IF(L22<=0,"No recent sales",Setup!$B$5+M22)) | O22: =IF($A22="","",Setup!$B$11) | P22: =IF($A22="","",ROUNDUP(L22*Setup!$B$12,0)) | Q22: =IF($A22="","",IF((E22+F22-G22)<0,0,IF(MAX(0,ROUNDUP(I22-H22,0))=0,0,CEILING(MAX(0,ROUNDUP(I22-H22,0)),Setup!$B$13)))) | R22: =IF($A22="","",IF(L22<=0,"No sales signal",N22-O22)) | S22: =IF($A22="","",IF((E22+F22-G22)<0,"Fix stock data",IF(R22="No sales signal","No action",IF(R22<=Setup!$B$5,"Order now",IF(R22<=Setup!$B$5+7,"Order this week",IF(H22<=I22,"Plan reorder","No action")))))) | T22: =IF($A22="","",IF((E22+F22-G22)<0,"Review stock data",IF(H22=0,"Out of stock",IF(H22<=I22,"Reorder soon","Healthy"))))
F23: =IF($A23="","",SUMIFS(Purchases!$D$5:$D$304,Purchases!$B$5:$B$304,$A23)) | G23: =IF($A23="","",SUMIFS(Sales!$D$5:$D$504,Sales!$B$5:$B$504,$A23)) | H23: =IF($A23="","",MAX(0,(E23+F23-G23))) | I23: =IF($A23="","",ROUNDUP(L23*O23+P23,0)) | K23: =IF($A23="","",H23*J23) | L23: =IF($A23="","",IFERROR(SUMIFS(Sales!$D$5:$D$504,Sales!$B$5:$B$504,$A23,Sales!$A$5:$A$504,">="&Setup!$B$5-Setup!$B$6,Sales!$A$5:$A$504,"<="&Setup!$B$5)/Setup!$B$6,0)) | M23: =IF($A23="","",IF(L23<=0,999,H23/L23)) | N23: =IF($A23="","",IF(L23<=0,"No recent sales",Setup!$B$5+M23)) | O23: =IF($A23="","",Setup!$B$11) | P23: =IF($A23="","",ROUNDUP(L23*Setup!$B$12,0)) | Q23: =IF($A23="","",IF((E23+F23-G23)<0,0,IF(MAX(0,ROUNDUP(I23-H23,0))=0,0,CEILING(MAX(0,ROUNDUP(I23-H23,0)),Setup!$B$13)))) | R23: =IF($A23="","",IF(L23<=0,"No sales signal",N23-O23)) | S23: =IF($A23="","",IF((E23+F23-G23)<0,"Fix stock data",IF(R23="No sales signal","No action",IF(R23<=Setup!$B$5,"Order now",IF(R23<=Setup!$B$5+7,"Order this week",IF(H23<=I23,"Plan reorder","No action")))))) | T23: =IF($A23="","",IF((E23+F23-G23)<0,"Review stock data",IF(H23=0,"Out of stock",IF(H23<=I23,"Reorder soon","Healthy"))))
F24: =IF($A24="","",SUMIFS(Purchases!$D$5:$D$304,Purchases!$B$5:$B$304,$A24)) | G24: =IF($A24="","",SUMIFS(Sales!$D$5:$D$504,Sales!$B$5:$B$504,$A24)) | H24: =IF($A24="","",MAX(0,(E24+F24-G24))) | I24: =IF($A24="","",ROUNDUP(L24*O24+P24,0)) | K24: =IF($A24="","",H24*J24) | L24: =IF($A24="","",IFERROR(SUMIFS(Sales!$D$5:$D$504,Sales!$B$5:$B$504,$A24,Sales!$A$5:$A$504,">="&Setup!$B$5-Setup!$B$6,Sales!$A$5:$A$504,"<="&Setup!$B$5)/Setup!$B$6,0)) | M24: =IF($A24="","",IF(L24<=0,999,H24/L24)) | N24: =IF($A24="","",IF(L24<=0,"No recent sales",Setup!$B$5+M24)) | O24: =IF($A24="","",Setup!$B$11) | P24: =IF($A24="","",ROUNDUP(L24*Setup!$B$12,0)) | Q24: =IF($A24="","",IF((E24+F24-G24)<0,0,IF(MAX(0,ROUNDUP(I24-H24,0))=0,0,CEILING(MAX(0,ROUNDUP(I24-H24,0)),Setup!$B$13)))) | R24: =IF($A24="","",IF(L24<=0,"No sales signal",N24-O24)) | S24: =IF($A24="","",IF((E24+F24-G24)<0,"Fix stock data",IF(R24="No sales signal","No action",IF(R24<=Setup!$B$5,"Order now",IF(R24<=Setup!$B$5+7,"Order this week",IF(H24<=I24,"Plan reorder","No action")))))) | T24: =IF($A24="","",IF((E24+F24-G24)<0,"Review stock data",IF(H24=0,"Out of stock",IF(H24<=I24,"Reorder soon","Healthy"))))
... F104: =IF($A104="","",SUMIFS(Purchases!$D$5:$D$304,Purchases!$B$5:$B$304,$A104)) | G104: =IF($A104="","",SUMIFS(Sales!$D$5:$D$504,Sales!$B$5:$B$504,$A104)) | H104: =IF($A104="","",MAX(0,(E104+F104-G104))) | I104: =IF($A104="","",ROUNDUP(L104*O104+P104,0)) | K104: =IF($A104="","",H104*J104) | L104: =IF($A104="","",IFERROR(SUMIFS(Sales!$D$5:$D$504,Sales!$B$5:$B$504,$A104,Sales!$A$5:$A$504,">="&Setup!$B$5-Setup!$B$6,Sales!$A$5:$A$504,"<="&Setup!$B$5)/Setup!$B$6,0)) | M104: =IF($A104="","",IF(L104<=0,999,H104/L104)) | N104: =IF($A104="","",IF(L104<=0,"No recent sales",Setup!$B$5+M104)) | O104: =IF($A104="","",Setup!$B$11) | P104: =IF($A104="","",ROUNDUP(L104*Setup!$B$12,0)) | Q104: =IF($A104="","",IF((E104+F104-G104)<0,0,IF(MAX(0,ROUNDUP(I104-H104,0))=0,0,CEILING(MAX(0,ROUNDUP(I104-H104,0)),Setup!$B$13)))) | R104: =IF($A104="","",IF(L104<=0,"No sales signal",N104-O104)) | S104: =IF($A104="","",IF((E104+F104-G104)<0,"Fix stock data",IF(R104="No sales signal","No action",IF(R104<=Setup!$B$5,"Order now",IF(R104<=Setup!$B$5+7,"Order this week",IF(H104<=I104,"Plan reorder","No action")))))) | T104: =IF($A104="","",IF((E104+F104-G104)<0,"Review stock data",IF(H104=0,"Out of stock",IF(H104<=I104,"Reorder soon","Healthy"))))
A105: Totals | E105: =SUM(E5:E104) | F105: =SUM(F5:F104) | G105: =SUM(G5:G104) | H105: =SUM(H5:H104) | K105: =SUM(K5:K104) | Q105: =SUM(Q5:Q104)

Sheet Purchases
A1: Purchases
A2: Log restocks and purchase costs. Quantity drives Inventory on-hand and total cost drives the dashboard.
A4: Date | B4: SKU | C4: Supplier | D4: Qty | E4: Unit Cost | F4: Shipping | G4: Total Cost | H4: Notes
A5: 46025 | B5: SKU-001 | C5: Northstar Wholesale | D5: 2 | E5: 0.95 | F5: 1.8 | G5: =IF(OR(B5="",D5=""),"",D5*E5+F5) | H5: Restock wave 1
A6: 46025 | B6: SKU-002 | C6: Northstar Wholesale | D6: 3 | E6: 1.12 | F6: 2.15 | G6: =IF(OR(B6="",D6=""),"",D6*E6+F6) | H6: Restock wave 1
A7: 46025 | B7: SKU-003 | C7: Northstar Wholesale | D7: 4 | E7: 1.29 | F7: 2.5 | G7: =IF(OR(B7="",D7=""),"",D7*E7+F7) | H7: Restock wave 1
A8: 46025 | B8: SKU-004 | C8: Northstar Wholesale | D8: 5 | E8: 1.46 | F8: 2.85 | G8: =IF(OR(B8="",D8=""),"",D8*E8+F8) | H8: Restock wave 1
A9: 46025 | B9: SKU-005 | C9: Northstar Wholesale | D9: 6 | E9: 1.63 | F9: 3.2 | G9: =IF(OR(B9="",D9=""),"",D9*E9+F9) | H9: Restock wave 1
A10: 46025 | B10: SKU-006 | C10: Harbor Supply | D10: 2 | E10: 2.1 | F10: 3.55 | G10: =IF(OR(B10="",D10=""),"",D10*E10+F10) | H10: Restock wave 1
A11: 46026 | B11: SKU-007 | C11: Harbor Supply | D11: 3 | E11: 2.27 | F11: 3.9 | G11: =IF(OR(B11="",D11=""),"",D11*E11+F11) | H11: Restock wave 1
A12: 46026 | B12: SKU-008 | C12: Harbor Supply | D12: 4 | E12: 2.44 | F12: 1.8 | G12: =IF(OR(B12="",D12=""),"",D12*E12+F12) | H12: Restock wave 1
A13: 46026 | B13: SKU-009 | C13: Harbor Supply | D13: 5 | E13: 2.61 | F13: 2.15 | G13: =IF(OR(B13="",D13=""),"",D13*E13+F13) | H13: Restock wave 1
A14: 46026 | B14: SKU-010 | C14: Harbor Supply | D14: 6 | E14: 2.78 | F14: 2.5 | G14: =IF(OR(B14="",D14=""),"",D14*E14+F14) | H14: Restock wave 1
A15: 46026 | B15: SKU-011 | C15: Paper Trail Co. | D15: 2 | E15: 1.25 | F15: 2.85 | G15: =IF(OR(B15="",D15=""),"",D15*E15+F15) | H15: Restock wave 1
A16: 46026 | B16: SKU-012 | C16: Paper Trail Co. | D16: 3 | E16: 1.42 | F16: 3.2 | G16: =IF(OR(B16="",D16=""),"",D16*E16+F16) | H16: Restock wave 1
... A20: 46027 | B20: SKU-016 | C20: Paper Trail Co. | D20: 2 | E20: 0.22 | F20: 2.15 | G20: =IF(OR(B20="",D20=""),"",D20*E20+F20) | H20: Restock wave 1
G21: =IF(OR(B21="",D21=""),"",D21*E21+F21)
G22: =IF(OR(B22="",D22=""),"",D22*E22+F22)
G23: =IF(OR(B23="",D23=""),"",D23*E23+F23)
G24: =IF(OR(B24="",D24=""),"",D24*E24+F24)
G25: =IF(OR(B25="",D25=""),"",D25*E25+F25)
G26: =IF(OR(B26="",D26=""),"",D26*E26+F26)
G27: =IF(OR(B27="",D27=""),"",D27*E27+F27)
G28: =IF(OR(B28="",D28=""),"",D28*E28+F28)
G29: =IF(OR(B29="",D29=""),"",D29*E29+F29)
G30: =IF(OR(B30="",D30=""),"",D30*E30+F30)
G31: =IF(OR(B31="",D31=""),"",D31*E31+F31)
G32: =IF(OR(B32="",D32=""),"",D32*E32+F32)
... G304: =IF(OR(B304="",D304=""),"",D304*E304+F304)
A305: Totals | D305: =SUM(D5:D304) | G305: =SUM(G5:G304)

Sheet Sales
A1: Sales
A2: Log sales orders and see revenue, fees, cost of goods sold, and gross profit.
A4: Date | B4: SKU | C4: Channel | D4: Qty | E4: Unit Price | F4: Fees | G4: Revenue | H4: COGS | I4: Gross Profit | J4: Notes
A5: 46068 | B5: SKU-001 | C5: Etsy | D5: 8 | E5: 2.75 | F5: 2.86 | G5: =IF(OR(B5="",D5=""),"",D5*E5) | H5: =IF(OR(B5="",D5=""),"",D5*VLOOKUP(B5,Inventory!$A$5:$J$104,10,FALSE)) | I5: =IF(G5="","",G5-F5-H5) | J5: Recent 30-day example sale 1
A6: 46068 | B6: SKU-002 | C6: Shop | D6: 6 | E6: 3.25 | F6: 2.54 | G6: =IF(OR(B6="",D6=""),"",D6*E6) | H6: =IF(OR(B6="",D6=""),"",D6*VLOOKUP(B6,Inventory!$A$5:$J$104,10,FALSE)) | I6: =IF(G6="","",G6-F6-H6) | J6: Recent 30-day example sale 1
A7: 46068 | B7: SKU-003 | C7: Market | D7: 4 | E7: 3.74 | F7: 1.94 | G7: =IF(OR(B7="",D7=""),"",D7*E7) | H7: =IF(OR(B7="",D7=""),"",D7*VLOOKUP(B7,Inventory!$A$5:$J$104,10,FALSE)) | I7: =IF(G7="","",G7-F7-H7) | J7: Recent 30-day example sale 1
A8: 46068 | B8: SKU-004 | C8: Retail | D8: 6 | E8: 4.23 | F8: 3.3 | G8: =IF(OR(B8="",D8=""),"",D8*E8) | H8: =IF(OR(B8="",D8=""),"",D8*VLOOKUP(B8,Inventory!$A$5:$J$104,10,FALSE)) | I8: =IF(G8="","",G8-F8-H8) | J8: Recent 30-day example sale 1
A9: 46068 | B9: SKU-005 | C9: Wholesale | D9: 2 | E9: 4.73 | F9: 1.23 | G9: =IF(OR(B9="",D9=""),"",D9*E9) | H9: =IF(OR(B9="",D9=""),"",D9*VLOOKUP(B9,Inventory!$A$5:$J$104,10,FALSE)) | I9: =IF(G9="","",G9-F9-H9) | J9: Recent 30-day example sale 1
A10: 46068 | B10: SKU-006 | C10: Etsy | D10: 4 | E10: 6.09 | F10: 3.17 | G10: =IF(OR(B10="",D10=""),"",D10*E10) | H10: =IF(OR(B10="",D10=""),"",D10*VLOOKUP(B10,Inventory!$A$5:$J$104,10,FALSE)) | I10: =IF(G10="","",G10-F10-H10) | J10: Recent 30-day example sale 1
A11: 46068 | B11: SKU-007 | C11: Shop | D11: 4 | E11: 6.58 | F11: 3.42 | G11: =IF(OR(B11="",D11=""),"",D11*E11) | H11: =IF(OR(B11="",D11=""),"",D11*VLOOKUP(B11,Inventory!$A$5:$J$104,10,FALSE)) | I11: =IF(G11="","",G11-F11-H11) | J11: Recent 30-day example sale 1
A12: 46068 | B12: SKU-008 | C12: Market | D12: 3 | E12: 7.08 | F12: 2.76 | G12: =IF(OR(B12="",D12=""),"",D12*E12) | H12: =IF(OR(B12="",D12=""),"",D12*VLOOKUP(B12,Inventory!$A$5:$J$104,10,FALSE)) | I12: =IF(G12="","",G12-F12-H12) | J12: Recent 30-day example sale 1
A13: 46082 | B13: SKU-001 | C13: Etsy | D13: 8 | E13: 2.75 | F13: 2.86 | G13: =IF(OR(B13="",D13=""),"",D13*E13) | H13: =IF(OR(B13="",D13=""),"",D13*VLOOKUP(B13,Inventory!$A$5:$J$104,10,FALSE)) | I13: =IF(G13="","",G13-F13-H13) | J13: Recent 30-day example sale 2
A14: 46082 | B14: SKU-002 | C14: Shop | D14: 7 | E14: 3.25 | F14: 2.96 | G14: =IF(OR(B14="",D14=""),"",D14*E14) | H14: =IF(OR(B14="",D14=""),"",D14*VLOOKUP(B14,Inventory!$A$5:$J$104,10,FALSE)) | I14: =IF(G14="","",G14-F14-H14) | J14: Recent 30-day example sale 2
A15: 46082 | B15: SKU-003 | C15: Market | D15: 5 | E15: 3.74 | F15: 2.43 | G15: =IF(OR(B15="",D15=""),"",D15*E15) | H15: =IF(OR(B15="",D15=""),"",D15*VLOOKUP(B15,Inventory!$A$5:$J$104,10,FALSE)) | I15: =IF(G15="","",G15-F15-H15) | J15: Recent 30-day example sale 2
A16: 46082 | B16: SKU-004 | C16: Retail | D16: 6 | E16: 4.23 | F16: 3.3 | G16: =IF(OR(B16="",D16=""),"",D16*E16) | H16: =IF(OR(B16="",D16=""),"",D16*VLOOKUP(B16,Inventory!$A$5:$J$104,10,FALSE)) | I16: =IF(G16="","",G16-F16-H16) | J16: Recent 30-day example sale 2
... A28: 46095 | B28: SKU-008 | C28: Market | D28: 4 | E28: 7.08 | F28: 3.68 | G28: =IF(OR(B28="",D28=""),"",D28*E28) | H28: =IF(OR(B28="",D28=""),"",D28*VLOOKUP(B28,Inventory!$A$5:$J$104,10,FALSE)) | I28: =IF(G28="","",G28-F28-H28) | J28: Recent 30-day example sale 3
G29: =IF(OR(B29="",D29=""),"",D29*E29) | H29: =IF(OR(B29="",D29=""),"",D29*VLOOKUP(B29,Inventory!$A$5:$J$104,10,FALSE)) | I29: =IF(G29="","",G29-F29-H29)
G30: =IF(OR(B30="",D30=""),"",D30*E30) | H30: =IF(OR(B30="",D30=""),"",D30*VLOOKUP(B30,Inventory!$A$5:$J$104,10,FALSE)) | I30: =IF(G30="","",G30-F30-H30)
G31: =IF(OR(B31="",D31=""),"",D31*E31) | H31: =IF(OR(B31="",D31=""),"",D31*VLOOKUP(B31,Inventory!$A$5:$J$104,10,FALSE)) | I31: =IF(G31="","",G31-F31-H31)
G32: =IF(OR(B32="",D32=""),"",D32*E32) | H32: =IF(OR(B32="",D32=""),"",D32*VLOOKUP(B32,Inventory!$A$5:$J$104,10,FALSE)) | I32: =IF(G32="","",G32-F32-H32)
G33: =IF(OR(B33="",D33=""),"",D33*E33) | H33: =IF(OR(B33="",D33=""),"",D33*VLOOKUP(B33,Inventory!$A$5:$J$104,10,FALSE)) | I33: =IF(G33="","",G33-F33-H33)
G34: =IF(OR(B34="",D34=""),"",D34*E34) | H34: =IF(OR(B34="",D34=""),"",D34*VLOOKUP(B34,Inventory!$A$5:$J$104,10,FALSE)) | I34: =IF(G34="","",G34-F34-H34)
G35: =IF(OR(B35="",D35=""),"",D35*E35) | H35: =IF(OR(B35="",D35=""),"",D35*VLOOKUP(B35,Inventory!$A$5:$J$104,10,FALSE)) | I35: =IF(G35="","",G35-F35-H35)
G36: =IF(OR(B36="",D36=""),"",D36*E36) | H36: =IF(OR(B36="",D36=""),"",D36*VLOOKUP(B36,Inventory!$A$5:$J$104,10,FALSE)) | I36: =IF(G36="","",G36-F36-H36)
G37: =IF(OR(B37="",D37=""),"",D37*E37) | H37: =IF(OR(B37="",D37=""),"",D37*VLOOKUP(B37,Inventory!$A$5:$J$104,10,FALSE)) | I37: =IF(G37="","",G37-F37-H37)
G38: =IF(OR(B38="",D38=""),"",D38*E38) | H38: =IF(OR(B38="",D38=""),"",D38*VLOOKUP(B38,Inventory!$A$5:$J$104,10,FALSE)) | I38: =IF(G38="","",G38-F38-H38)
G39: =IF(OR(B39="",D39=""),"",D39*E39) | H39: =IF(OR(B39="",D39=""),"",D39*VLOOKUP(B39,Inventory!$A$5:$J$104,10,FALSE)) | I39: =IF(G39="","",G39-F39-H39)
G40: =IF(OR(B40="",D40=""),"",D40*E40) | H40: =IF(OR(B40="",D40=""),"",D40*VLOOKUP(B40,Inventory!$A$5:$J$104,10,FALSE)) | I40: =IF(G40="","",G40-F40-H40)
... G504: =IF(OR(B504="",D504=""),"",D504*E504) | H504: =IF(OR(B504="",D504=""),"",D504*VLOOKUP(B504,Inventory!$A$5:$J$104,10,FALSE)) | I504: =IF(G504="","",G504-F504-H504)
A505: Totals | D505: =SUM(D5:D504) | G505: =SUM(G5:G504) | H505: =SUM(H5:H504) | I505: =SUM(I5:I504)

Sheet Price Calculator
A1: Price Calculator
A2: Test sale price, expected profit, and margin before you list a product.
A4: Product | B4: SKU | C4: COGS | D4: Packaging | E4: Labor | F4: Overhead | G4: Fee % | H4: Tax % | I4: Target Margin | J4: Suggested Price | K4: Profit | L4: Margin | M4: Notes
A5: Canvas Tote - Sand | B5: SKU-001 | C5: =IF(B5="","",VLOOKUP(B5,Inventory!$A$5:$J$104,10,FALSE)) | D5: 0.18 | E5: 0.44 | F5: 0.25 | G5: 0.13 | H5: 0.1 | I5: 0.42 | J5: =IF(B5="","",ROUND((C5+D5+E5+F5)/(1-(G5+H5+I5)),2)) | K5: =IF(J5="","",J5-(C5+D5+E5+F5)-(J5*G5)-(J5*H5)) | L5: =IF(J5="","",IF(J5=0,"",K5/J5)) | M5: Pricing scenario 1
A6: Canvas Tote - Olive | B6: SKU-002 | C6: =IF(B6="","",VLOOKUP(B6,Inventory!$A$5:$J$104,10,FALSE)) | D6: 0.25 | E6: 0.53 | F6: 0.25 | G6: 0.13 | H6: 0.1 | I6: 0.45 | J6: =IF(B6="","",ROUND((C6+D6+E6+F6)/(1-(G6+H6+I6)),2)) | K6: =IF(J6="","",J6-(C6+D6+E6+F6)-(J6*G6)-(J6*H6)) | L6: =IF(J6="","",IF(J6=0,"",K6/J6)) | M6: Pricing scenario 2
A7: Canvas Tote - Slate | B7: SKU-003 | C7: =IF(B7="","",VLOOKUP(B7,Inventory!$A$5:$J$104,10,FALSE)) | D7: 0.32 | E7: 0.62 | F7: 0.25 | G7: 0.13 | H7: 0.1 | I7: 0.48 | J7: =IF(B7="","",ROUND((C7+D7+E7+F7)/(1-(G7+H7+I7)),2)) | K7: =IF(J7="","",J7-(C7+D7+E7+F7)-(J7*G7)-(J7*H7)) | L7: =IF(J7="","",IF(J7=0,"",K7/J7)) | M7: Pricing scenario 3
A8: Canvas Tote - Coral | B8: SKU-004 | C8: =IF(B8="","",VLOOKUP(B8,Inventory!$A$5:$J$104,10,FALSE)) | D8: 0.39 | E8: 0.71 | F8: 0.25 | G8: 0.13 | H8: 0.1 | I8: 0.42 | J8: =IF(B8="","",ROUND((C8+D8+E8+F8)/(1-(G8+H8+I8)),2)) | K8: =IF(J8="","",J8-(C8+D8+E8+F8)-(J8*G8)-(J8*H8)) | L8: =IF(J8="","",IF(J8=0,"",K8/J8)) | M8: Pricing scenario 4
A9: Canvas Tote - Natural | B9: SKU-005 | C9: =IF(B9="","",VLOOKUP(B9,Inventory!$A$5:$J$104,10,FALSE)) | D9: 0.18 | E9: 0.8 | F9: 0.25 | G9: 0.13 | H9: 0.1 | I9: 0.45 | J9: =IF(B9="","",ROUND((C9+D9+E9+F9)/(1-(G9+H9+I9)),2)) | K9: =IF(J9="","",J9-(C9+D9+E9+F9)-(J9*G9)-(J9*H9)) | L9: =IF(J9="","",IF(J9=0,"",K9/J9)) | M9: Pricing scenario 5
A10: Ceramic Mug - Sand | B10: SKU-006 | C10: =IF(B10="","",VLOOKUP(B10,Inventory!$A$5:$J$104,10,FALSE)) | D10: 0.25 | E10: 0.44 | F10: 0.25 | G10: 0.13 | H10: 0.1 | I10: 0.48 | J10: =IF(B10="","",ROUND((C10+D10+E10+F10)/(1-(G10+H10+I10)),2)) | K10: =IF(J10="","",J10-(C10+D10+E10+F10)-(J10*G10)-(J10*H10)) | L10: =IF(J10="","",IF(J10=0,"",K10/J10)) | M10: Pricing scenario 6
A11: Ceramic Mug - Olive | B11: SKU-007 | C11: =IF(B11="","",VLOOKUP(B11,Inventory!$A$5:$J$104,10,FALSE)) | D11: 0.32 | E11: 0.53 | F11: 0.25 | G11: 0.13 | H11: 0.1 | I11: 0.42 | J11: =IF(B11="","",ROUND((C11+D11+E11+F11)/(1-(G11+H11+I11)),2)) | K11: =IF(J11="","",J11-(C11+D11+E11+F11)-(J11*G11)-(J11*H11)) | L11: =IF(J11="","",IF(J11=0,"",K11/J11)) | M11: Pricing scenario 7
A12: Ceramic Mug - Slate | B12: SKU-008 | C12: =IF(B12="","",VLOOKUP(B12,Inventory!$A$5:$J$104,10,FALSE)) | D12: 0.39 | E12: 0.62 | F12: 0.25 | G12: 0.13 | H12: 0.1 | I12: 0.45 | J12: =IF(B12="","",ROUND((C12+D12+E12+F12)/(1-(G12+H12+I12)),2)) | K12: =IF(J12="","",J12-(C12+D12+E12+F12)-(J12*G12)-(J12*H12)) | L12: =IF(J12="","",IF(J12=0,"",K12/J12)) | M12: Pricing scenario 8
C13: =IF(B13="","",VLOOKUP(B13,Inventory!$A$5:$J$104,10,FALSE)) | J13: =IF(B13="","",ROUND((C13+D13+E13+F13)/(1-(G13+H13+I13)),2)) | K13: =IF(J13="","",J13-(C13+D13+E13+F13)-(J13*G13)-(J13*H13)) | L13: =IF(J13="","",IF(J13=0,"",K13/J13))
C14: =IF(B14="","",VLOOKUP(B14,Inventory!$A$5:$J$104,10,FALSE)) | J14: =IF(B14="","",ROUND((C14+D14+E14+F14)/(1-(G14+H14+I14)),2)) | K14: =IF(J14="","",J14-(C14+D14+E14+F14)-(J14*G14)-(J14*H14)) | L14: =IF(J14="","",IF(J14=0,"",K14/J14))
C15: =IF(B15="","",VLOOKUP(B15,Inventory!$A$5:$J$104,10,FALSE)) | J15: =IF(B15="","",ROUND((C15+D15+E15+F15)/(1-(G15+H15+I15)),2)) | K15: =IF(J15="","",J15-(C15+D15+E15+F15)-(J15*G15)-(J15*H15)) | L15: =IF(J15="","",IF(J15=0,"",K15/J15))
C16: =IF(B16="","",VLOOKUP(B16,Inventory!$A$5:$J$104,10,FALSE)) | J16: =IF(B16="","",ROUND((C16+D16+E16+F16)/(1-(G16+H16+I16)),2)) | K16: =IF(J16="","",J16-(C16+D16+E16+F16)-(J16*G16)-(J16*H16)) | L16: =IF(J16="","",IF(J16=0,"",K16/J16))
C17: =IF(B17="","",VLOOKUP(B17,Inventory!$A$5:$J$104,10,FALSE)) | J17: =IF(B17="","",ROUND((C17+D17+E17+F17)/(1-(G17+H17+I17)),2)) | K17: =IF(J17="","",J17-(C17+D17+E17+F17)-(J17*G17)-(J17*H17)) | L17: =IF(J17="","",IF(J17=0,"",K17/J17))
C18: =IF(B18="","",VLOOKUP(B18,Inventory!$A$5:$J$104,10,FALSE)) | J18: =IF(B18="","",ROUND((C18+D18+E18+F18)/(1-(G18+H18+I18)),2)) | K18: =IF(J18="","",J18-(C18+D18+E18+F18)-(J18*G18)-(J18*H18)) | L18: =IF(J18="","",IF(J18=0,"",K18/J18))
C19: =IF(B19="","",VLOOKUP(B19,Inventory!$A$5:$J$104,10,FALSE)) | J19: =IF(B19="","",ROUND((C19+D19+E19+F19)/(1-(G19+H19+I19)),2)) | K19: =IF(J19="","",J19-(C19+D19+E19+F19)-(J19*G19)-(J19*H19)) | L19: =IF(J19="","",IF(J19=0,"",K19/J19))
C20: =IF(B20="","",VLOOKUP(B20,Inventory!$A$5:$J$104,10,FALSE)) | J20: =IF(B20="","",ROUND((C20+D20+E20+F20)/(1-(G20+H20+I20)),2)) | K20: =IF(J20="","",J20-(C20+D20+E20+F20)-(J20*G20)-(J20*H20)) | L20: =IF(J20="","",IF(J20=0,"",K20/J20))
C21: =IF(B21="","",VLOOKUP(B21,Inventory!$A$5:$J$104,10,FALSE)) | J21: =IF(B21="","",ROUND((C21+D21+E21+F21)/(1-(G21+H21+I21)),2)) | K21: =IF(J21="","",J21-(C21+D21+E21+F21)-(J21*G21)-(J21*H21)) | L21: =IF(J21="","",IF(J21=0,"",K21/J21))
C22: =IF(B22="","",VLOOKUP(B22,Inventory!$A$5:$J$104,10,FALSE)) | J22: =IF(B22="","",ROUND((C22+D22+E22+F22)/(1-(G22+H22+I22)),2)) | K22: =IF(J22="","",J22-(C22+D22+E22+F22)-(J22*G22)-(J22*H22)) | L22: =IF(J22="","",IF(J22=0,"",K22/J22))
C23: =IF(B23="","",VLOOKUP(B23,Inventory!$A$5:$J$104,10,FALSE)) | J23: =IF(B23="","",ROUND((C23+D23+E23+F23)/(1-(G23+H23+I23)),2)) | K23: =IF(J23="","",J23-(C23+D23+E23+F23)-(J23*G23)-(J23*H23)) | L23: =IF(J23="","",IF(J23=0,"",K23/J23))
C24: =IF(B24="","",VLOOKUP(B24,Inventory!$A$5:$J$104,10,FALSE)) | J24: =IF(B24="","",ROUND((C24+D24+E24+F24)/(1-(G24+H24+I24)),2)) | K24: =IF(J24="","",J24-(C24+D24+E24+F24)-(J24*G24)-(J24*H24)) | L24: =IF(J24="","",IF(J24=0,"",K24/J24))
... C104: =IF(B104="","",VLOOKUP(B104,Inventory!$A$5:$J$104,10,FALSE)) | J104: =IF(B104="","",ROUND((C104+D104+E104+F104)/(1-(G104+H104+I104)),2)) | K104: =IF(J104="","",J104-(C104+D104+E104+F104)-(J104*G104)-(J104*H104)) | L104: =IF(J104="","",IF(J104=0,"",K104/J104))

Sheet Price List
A1: Price List
A2: Save approved price snapshots here. The top row mirrors the calculator output for quick reuse.
A4: Date | B4: SKU | C4: Product | D4: Cost | E4: Suggested Price | F4: Profit | G4: Margin | H4: Status | I4: Notes
A5: 46042 | B5: SKU-001 | C5: Canvas Tote - Sand | D5: =IF(B5="","",VLOOKUP(B5,Inventory!$A$5:$J$104,10,FALSE)) | E5: ='Price Calculator'!J5 | F5: ='Price Calculator'!K5 | G5: ='Price Calculator'!L5 | H5: =IF(B5="","",IF(G5>=0.45,"Good margin","Review")) | I5: Pricing scenario 1
A6: 46043 | B6: SKU-002 | C6: Canvas Tote - Olive | D6: =IF(B6="","",VLOOKUP(B6,Inventory!$A$5:$J$104,10,FALSE)) | E6: ='Price Calculator'!J6 | F6: ='Price Calculator'!K6 | G6: ='Price Calculator'!L6 | H6: =IF(B6="","",IF(G6>=0.45,"Good margin","Review")) | I6: Pricing scenario 2
A7: 46044 | B7: SKU-003 | C7: Canvas Tote - Slate | D7: =IF(B7="","",VLOOKUP(B7,Inventory!$A$5:$J$104,10,FALSE)) | E7: ='Price Calculator'!J7 | F7: ='Price Calculator'!K7 | G7: ='Price Calculator'!L7 | H7: =IF(B7="","",IF(G7>=0.45,"Good margin","Review")) | I7: Pricing scenario 3
A8: 46045 | B8: SKU-004 | C8: Canvas Tote - Coral | D8: =IF(B8="","",VLOOKUP(B8,Inventory!$A$5:$J$104,10,FALSE)) | E8: ='Price Calculator'!J8 | F8: ='Price Calculator'!K8 | G8: ='Price Calculator'!L8 | H8: =IF(B8="","",IF(G8>=0.45,"Good margin","Review")) | I8: Pricing scenario 4
A9: 46046 | B9: SKU-005 | C9: Canvas Tote - Natural | D9: =IF(B9="","",VLOOKUP(B9,Inventory!$A$5:$J$104,10,FALSE)) | E9: ='Price Calculator'!J9 | F9: ='Price Calculator'!K9 | G9: ='Price Calculator'!L9 | H9: =IF(B9="","",IF(G9>=0.45,"Good margin","Review")) | I9: Pricing scenario 5
A10: 46047 | B10: SKU-006 | C10: Ceramic Mug - Sand | D10: =IF(B10="","",VLOOKUP(B10,Inventory!$A$5:$J$104,10,FALSE)) | E10: ='Price Calculator'!J10 | F10: ='Price Calculator'!K10 | G10: ='Price Calculator'!L10 | H10: =IF(B10="","",IF(G10>=0.45,"Good margin","Review")) | I10: Pricing scenario 6
A11: 46048 | B11: SKU-007 | C11: Ceramic Mug - Olive | D11: =IF(B11="","",VLOOKUP(B11,Inventory!$A$5:$J$104,10,FALSE)) | E11: ='Price Calculator'!J11 | F11: ='Price Calculator'!K11 | G11: ='Price Calculator'!L11 | H11: =IF(B11="","",IF(G11>=0.45,"Good margin","Review")) | I11: Pricing scenario 7
A12: 46049 | B12: SKU-008 | C12: Ceramic Mug - Slate | D12: =IF(B12="","",VLOOKUP(B12,Inventory!$A$5:$J$104,10,FALSE)) | E12: ='Price Calculator'!J12 | F12: ='Price Calculator'!K12 | G12: ='Price Calculator'!L12 | H12: =IF(B12="","",IF(G12>=0.45,"Good margin","Review")) | I12: Pricing scenario 8
D13: =IF(B13="","",VLOOKUP(B13,Inventory!$A$5:$J$104,10,FALSE)) | E13: ='Price Calculator'!J13 | F13: ='Price Calculator'!K13 | G13: ='Price Calculator'!L13 | H13: =IF(B13="","",IF(G13>=0.45,"Good margin","Review"))
D14: =IF(B14="","",VLOOKUP(B14,Inventory!$A$5:$J$104,10,FALSE)) | E14: ='Price Calculator'!J14 | F14: ='Price Calculator'!K14 | G14: ='Price Calculator'!L14 | H14: =IF(B14="","",IF(G14>=0.45,"Good margin","Review"))
D15: =IF(B15="","",VLOOKUP(B15,Inventory!$A$5:$J$104,10,FALSE)) | E15: ='Price Calculator'!J15 | F15: ='Price Calculator'!K15 | G15: ='Price Calculator'!L15 | H15: =IF(B15="","",IF(G15>=0.45,"Good margin","Review"))
D16: =IF(B16="","",VLOOKUP(B16,Inventory!$A$5:$J$104,10,FALSE)) | E16: ='Price Calculator'!J16 | F16: ='Price Calculator'!K16 | G16: ='Price Calculator'!L16 | H16: =IF(B16="","",IF(G16>=0.45,"Good margin","Review"))
D17: =IF(B17="","",VLOOKUP(B17,Inventory!$A$5:$J$104,10,FALSE)) | E17: ='Price Calculator'!J17 | F17: ='Price Calculator'!K17 | G17: ='Price Calculator'!L17 | H17: =IF(B17="","",IF(G17>=0.45,"Good margin","Review"))
D18: =IF(B18="","",VLOOKUP(B18,Inventory!$A$5:$J$104,10,FALSE)) | E18: ='Price Calculator'!J18 | F18: ='Price Calculator'!K18 | G18: ='Price Calculator'!L18 | H18: =IF(B18="","",IF(G18>=0.45,"Good margin","Review"))
D19: =IF(B19="","",VLOOKUP(B19,Inventory!$A$5:$J$104,10,FALSE)) | E19: ='Price Calculator'!J19 | F19: ='Price Calculator'!K19 | G19: ='Price Calculator'!L19 | H19: =IF(B19="","",IF(G19>=0.45,"Good margin","Review"))
D20: =IF(B20="","",VLOOKUP(B20,Inventory!$A$5:$J$104,10,FALSE)) | E20: ='Price Calculator'!J20 | F20: ='Price Calculator'!K20 | G20: ='Price Calculator'!L20 | H20: =IF(B20="","",IF(G20>=0.45,"Good margin","Review"))
D21: =IF(B21="","",VLOOKUP(B21,Inventory!$A$5:$J$104,10,FALSE)) | E21: ='Price Calculator'!J21 | F21: ='Price Calculator'!K21 | G21: ='Price Calculator'!L21 | H21: =IF(B21="","",IF(G21>=0.45,"Good margin","Review"))
D22: =IF(B22="","",VLOOKUP(B22,Inventory!$A$5:$J$104,10,FALSE)) | E22: ='Price Calculator'!J22 | F22: ='Price Calculator'!K22 | G22: ='Price Calculator'!L22 | H22: =IF(B22="","",IF(G22>=0.45,"Good margin","Review"))
D23: =IF(B23="","",VLOOKUP(B23,Inventory!$A$5:$J$104,10,FALSE)) | E23: ='Price Calculator'!J23 | F23: ='Price Calculator'!K23 | G23: ='Price Calculator'!L23 | H23: =IF(B23="","",IF(G23>=0.45,"Good margin","Review"))
D24: =IF(B24="","",VLOOKUP(B24,Inventory!$A$5:$J$104,10,FALSE)) | E24: ='Price Calculator'!J24 | F24: ='Price Calculator'!K24 | G24: ='Price Calculator'!L24 | H24: =IF(B24="","",IF(G24>=0.45,"Good margin","Review"))
... D104: =IF(B104="","",VLOOKUP(B104,Inventory!$A$5:$J$104,10,FALSE)) | E104: ='Price Calculator'!J104 | F104: ='Price Calculator'!K104 | G104: ='Price Calculator'!L104 | H104: =IF(B104="","",IF(G104>=0.45,"Good margin","Review"))

Sheet Help
A1: Help
A2: Plain-English workflow, compatibility, limits, and support scope.
A4: Compatible with
A5: • Excel-compatible spreadsheet editors
A6: • Google Sheets standard-formula import
A8: You can change
A9: • Yellow input cells in Setup, except the derived reorder-point policy note
A10: • Yellow blank rows on Inventory, Purchases, Sales, Price Calculator, and Price List
A12: Leave alone
A13: • Dashboard formulas and charts
A14: • Inventory derived reorder point, on-hand, action, and status formulas
A15: • Sales profit formulas
... A28: • Imported protection settings can vary by editor or account.

Sheet Lists
A1: SKUs | B1: Categories
A2: SKU-001 | B2: Accessories
A3: SKU-002 | B3: Drinkware
A4: SKU-003 | B4: Stationery
A5: SKU-004 | B5: Home
A6: SKU-005 | B6: Wall Art
A7: SKU-006 | B7: Apparel
A8: SKU-007
A9: SKU-008
A10: SKU-009
A11: SKU-010
A12: SKU-011
A13: SKU-012
A14: SKU-013
A15: SKU-014
A16: SKU-015
A17: SKU-016
A18: SKU-017
A19: SKU-018
... A101: SKU-100
